<annotation><folder>images</folder><filename>ar_alstom_2014_noneng_68_2.jpg</filename><path>all_images/ar_alstom_2014_noneng_68_2.jpg</path><source><database>Unknown</database></source><size><width>707</width><height>386</height><depth>3</depth></size><segmentated>0</segmentated><object><name>table</name><pose>Unspecified</pose><truncated>0</truncated><difficult>0</difficult><bndbox><xmin>0</xmin><ymin>0</ymin><xmax>707</xmax><ymax>386</ymax></bndbox><columns><column><dont_care>False</dont_care><x0>17</x0><x1>255</x1><y0>11</y0><y1>371</y1></column><column><dont_care>False</dont_care><x0>255</x0><x1>334</x1><y0>11</y0><y1>371</y1></column><column><dont_care>False</dont_care><x0>334</x0><x1>434</x1><y0>11</y0><y1>371</y1></column><column><dont_care>False</dont_care><x0>434</x0><x1>541</x1><y0>11</y0><y1>371</y1></column><column><dont_care>False</dont_care><x0>541</x0><x1>615</x1><y0>11</y0><y1>371</y1></column><column><dont_care>False</dont_care><x0>615</x0><x1>695</x1><y0>11</y0><y1>371</y1></column></columns></object></annotation>