<annotation><folder>images</folder><filename>ar_alstom_2011_eng_18_2.jpg</filename><path>all_images/ar_alstom_2011_eng_18_2.jpg</path><source><database>Unknown</database></source><size><width>714</width><height>284</height><depth>3</depth></size><segmentated>0</segmentated><object><name>table</name><pose>Unspecified</pose><truncated>0</truncated><difficult>0</difficult><bndbox><xmin>0</xmin><ymin>0</ymin><xmax>714</xmax><ymax>284</ymax></bndbox><columns><column><dont_care>False</dont_care><x0>20</x0><x1>212</x1><y0>13</y0><y1>267</y1></column><column><dont_care>False</dont_care><x0>212</x0><x1>263</x1><y0>13</y0><y1>267</y1></column><column><dont_care>False</dont_care><x0>263</x0><x1>369</x1><y0>13</y0><y1>33</y1></column><column><dont_care>False</dont_care><x0>263</x0><x1>307</x1><y0>33</y0><y1>267</y1></column><column><dont_care>False</dont_care><x0>307</x0><x1>369</x1><y0>33</y0><y1>267</y1></column><column><dont_care>False</dont_care><x0>369</x0><x1>477</x1><y0>13</y0><y1>33</y1></column><column><dont_care>False</dont_care><x0>369</x0><x1>422</x1><y0>33</y0><y1>267</y1></column><column><dont_care>False</dont_care><x0>422</x0><x1>477</x1><y0>33</y0><y1>267</y1></column><column><dont_care>False</dont_care><x0>477</x0><x1>588</x1><y0>13</y0><y1>33</y1></column><column><dont_care>False</dont_care><x0>477</x0><x1>532</x1><y0>33</y0><y1>267</y1></column><column><dont_care>False</dont_care><x0>532</x0><x1>588</x1><y0>33</y0><y1>267</y1></column><column><dont_care>False</dont_care><x0>588</x0><x1>698</x1><y0>13</y0><y1>33</y1></column><column><dont_care>False</dont_care><x0>588</x0><x1>638</x1><y0>33</y0><y1>267</y1></column><column><dont_care>False</dont_care><x0>638</x0><x1>698</x1><y0>33</y0><y1>267</y1></column></columns></object></annotation>