<annotation><folder>images</folder><filename>ar_alstom_2014_eng_90_1.jpg</filename><path>all_images/ar_alstom_2014_eng_90_1.jpg</path><source><database>Unknown</database></source><size><width>728</width><height>225</height><depth>3</depth></size><segmentated>0</segmentated><object><name>table</name><pose>Unspecified</pose><truncated>0</truncated><difficult>0</difficult><bndbox><xmin>0</xmin><ymin>0</ymin><xmax>728</xmax><ymax>225</ymax></bndbox><columns><column><dont_care>False</dont_care><x0>26</x0><x1>176</x1><y0>17</y0><y1>203</y1></column><column><dont_care>False</dont_care><x0>176</x0><x1>522</x1><y0>17</y0><y1>38</y1></column><column><dont_care>False</dont_care><x0>176</x0><x1>258</x1><y0>38</y0><y1>203</y1></column><column><dont_care>False</dont_care><x0>258</x0><x1>343</x1><y0>38</y0><y1>203</y1></column><column><dont_care>False</dont_care><x0>343</x0><x1>420</x1><y0>38</y0><y1>203</y1></column><column><dont_care>False</dont_care><x0>420</x0><x1>522</x1><y0>38</y0><y1>203</y1></column><column><dont_care>False</dont_care><x0>522</x0><x1>702</x1><y0>17</y0><y1>38</y1></column><column><dont_care>False</dont_care><x0>522</x0><x1>606</x1><y0>38</y0><y1>203</y1></column><column><dont_care>False</dont_care><x0>606</x0><x1>702</x1><y0>38</y0><y1>203</y1></column></columns></object></annotation>