<annotation><folder>images</folder><filename>ar_alstom_2014_eng_18_2.jpg</filename><path>all_images/ar_alstom_2014_eng_18_2.jpg</path><source><database>Unknown</database></source><size><width>709</width><height>93</height><depth>3</depth></size><segmentated>0</segmentated><object><name>table</name><pose>Unspecified</pose><truncated>0</truncated><difficult>0</difficult><bndbox><xmin>0</xmin><ymin>0</ymin><xmax>709</xmax><ymax>93</ymax></bndbox><columns><column><dont_care>False</dont_care><x0>13</x0><x1>437</x1><y0>26</y0><y1>81</y1></column><column><dont_care>False</dont_care><x0>437</x0><x1>510</x1><y0>26</y0><y1>81</y1></column><column><dont_care>False</dont_care><x0>510</x0><x1>587</x1><y0>26</y0><y1>81</y1></column><column><dont_care>False</dont_care><x0>587</x0><x1>690</x1><y0>26</y0><y1>81</y1></column></columns></object></annotation>