<annotation><folder>images</folder><filename>ar_basf_2019_noneng_67_1.jpg</filename><path>all_images/ar_basf_2019_noneng_67_1.jpg</path><source><database>Unknown</database></source><size><width>698</width><height>341</height><depth>3</depth></size><segmentated>0</segmentated><object><name>table</name><pose>Unspecified</pose><truncated>0</truncated><difficult>0</difficult><bndbox><xmin>0</xmin><ymin>0</ymin><xmax>698</xmax><ymax>341</ymax></bndbox><columns><column><dont_care>False</dont_care><x0>11</x0><x1>301</x1><y0>41</y0><y1>322</y1></column><column><dont_care>False</dont_care><x0>301</x0><x1>493</x1><y0>41</y0><y1>57</y1></column><column><dont_care>False</dont_care><x0>301</x0><x1>398</x1><y0>57</y0><y1>322</y1></column><column><dont_care>False</dont_care><x0>398</x0><x1>493</x1><y0>57</y0><y1>322</y1></column><column><dont_care>False</dont_care><x0>493</x0><x1>684</x1><y0>41</y0><y1>57</y1></column><column><dont_care>False</dont_care><x0>493</x0><x1>592</x1><y0>57</y0><y1>322</y1></column><column><dont_care>False</dont_care><x0>592</x0><x1>684</x1><y0>57</y0><y1>322</y1></column></columns></object></annotation>