<annotation><folder>images</folder><filename>ar_bouygues_2018_eng_18_1.jpg</filename><path>all_images/ar_bouygues_2018_eng_18_1.jpg</path><source><database>Unknown</database></source><size><width>534</width><height>519</height><depth>3</depth></size><segmentated>0</segmentated><object><name>table</name><pose>Unspecified</pose><truncated>0</truncated><difficult>0</difficult><bndbox><xmin>0</xmin><ymin>0</ymin><xmax>534</xmax><ymax>519</ymax></bndbox><columns><column><dont_care>False</dont_care><x0>18</x0><x1>360</x1><y0>14</y0><y1>505</y1></column><column><dont_care>False</dont_care><x0>360</x0><x1>443</x1><y0>14</y0><y1>505</y1></column><column><dont_care>False</dont_care><x0>443</x0><x1>522</x1><y0>14</y0><y1>505</y1></column></columns></object></annotation>