<annotation><folder>images</folder><filename>ar_basf_2009_noneng_72_0.jpg</filename><path>all_images/ar_basf_2009_noneng_72_0.jpg</path><source><database>Unknown</database></source><size><width>694</width><height>298</height><depth>3</depth></size><segmentated>0</segmentated><object><name>table</name><pose>Unspecified</pose><truncated>0</truncated><difficult>0</difficult><bndbox><xmin>0</xmin><ymin>0</ymin><xmax>694</xmax><ymax>298</ymax></bndbox><columns><column><dont_care>False</dont_care><x0>13</x0><x1>371</x1><y0>39</y0><y1>286</y1></column><column><dont_care>False</dont_care><x0>371</x0><x1>478</x1><y0>39</y0><y1>286</y1></column><column><dont_care>False</dont_care><x0>478</x0><x1>584</x1><y0>39</y0><y1>286</y1></column><column><dont_care>False</dont_care><x0>584</x0><x1>687</x1><y0>39</y0><y1>286</y1></column></columns></object></annotation>