<annotation><folder>images</folder><filename>ar_basf_2011_noneng_56_0.jpg</filename><path>all_images/ar_basf_2011_noneng_56_0.jpg</path><source><database>Unknown</database></source><size><width>697</width><height>804</height><depth>3</depth></size><segmentated>0</segmentated><object><name>table</name><pose>Unspecified</pose><truncated>0</truncated><difficult>0</difficult><bndbox><xmin>0</xmin><ymin>0</ymin><xmax>697</xmax><ymax>804</ymax></bndbox><columns><column><dont_care>False</dont_care><x0>12</x0><x1>89</x1><y0>13</y0><y1>795</y1></column><column><dont_care>False</dont_care><x0>89</x0><x1>158</x1><y0>13</y0><y1>795</y1></column><column><dont_care>False</dont_care><x0>158</x0><x1>228</x1><y0>13</y0><y1>795</y1></column><column><dont_care>False</dont_care><x0>228</x0><x1>305</x1><y0>13</y0><y1>795</y1></column><column><dont_care>False</dont_care><x0>305</x0><x1>685</x1><y0>13</y0><y1>795</y1></column></columns></object></annotation>