<annotation><folder>images</folder><filename>ar_basf_2011_noneng_109_0.jpg</filename><path>all_images/ar_basf_2011_noneng_109_0.jpg</path><source><database>Unknown</database></source><size><width>705</width><height>338</height><depth>3</depth></size><segmentated>0</segmentated><object><name>table</name><pose>Unspecified</pose><truncated>0</truncated><difficult>0</difficult><bndbox><xmin>0</xmin><ymin>0</ymin><xmax>705</xmax><ymax>338</ymax></bndbox><columns><column><dont_care>False</dont_care><x0>15</x0><x1>375</x1><y0>40</y0><y1>319</y1></column><column><dont_care>False</dont_care><x0>375</x0><x1>484</x1><y0>40</y0><y1>319</y1></column><column><dont_care>False</dont_care><x0>484</x0><x1>587</x1><y0>40</y0><y1>319</y1></column><column><dont_care>False</dont_care><x0>587</x0><x1>694</x1><y0>40</y0><y1>319</y1></column></columns></object></annotation>