<annotation><folder>images</folder><filename>ar_deutschebank_2013_noneng_119_0.jpg</filename><path>all_images/ar_deutschebank_2013_noneng_119_0.jpg</path><source><database>Unknown</database></source><size><width>726</width><height>459</height><depth>3</depth></size><segmentated>0</segmentated><object><name>table</name><pose>Unspecified</pose><truncated>0</truncated><difficult>0</difficult><bndbox><xmin>0</xmin><ymin>0</ymin><xmax>726</xmax><ymax>459</ymax></bndbox><columns><column><dont_care>False</dont_care><x0>16</x0><x1>132</x1><y0>10</y0><y1>447</y1></column><column><dont_care>False</dont_care><x0>132</x0><x1>193</x1><y0>10</y0><y1>447</y1></column><column><dont_care>False</dont_care><x0>193</x0><x1>260</x1><y0>10</y0><y1>447</y1></column><column><dont_care>False</dont_care><x0>260</x0><x1>323</x1><y0>10</y0><y1>447</y1></column><column><dont_care>False</dont_care><x0>323</x0><x1>389</x1><y0>10</y0><y1>447</y1></column><column><dont_care>False</dont_care><x0>389</x0><x1>453</x1><y0>10</y0><y1>447</y1></column><column><dont_care>False</dont_care><x0>453</x0><x1>516</x1><y0>10</y0><y1>447</y1></column><column><dont_care>False</dont_care><x0>516</x0><x1>585</x1><y0>10</y0><y1>447</y1></column><column><dont_care>False</dont_care><x0>585</x0><x1>647</x1><y0>10</y0><y1>447</y1></column><column><dont_care>False</dont_care><x0>647</x0><x1>710</x1><y0>10</y0><y1>447</y1></column></columns></object></annotation>