<annotation><folder>images</folder><filename>ar_enel_2017_eng_159_1.jpg</filename><path>all_images/ar_enel_2017_eng_159_1.jpg</path><source><database>Unknown</database></source><size><width>703</width><height>426</height><depth>3</depth></size><segmentated>0</segmentated><object><name>table</name><pose>Unspecified</pose><truncated>0</truncated><difficult>0</difficult><bndbox><xmin>0</xmin><ymin>0</ymin><xmax>703</xmax><ymax>426</ymax></bndbox><columns><column><dont_care>False</dont_care><x0>16</x0><x1>139</x1><y0>25</y0><y1>411</y1></column><column><dont_care>False</dont_care><x0>139</x0><x1>227</x1><y0>25</y0><y1>63</y1></column><column><dont_care>False</dont_care><x0>139</x0><x1>227</x1><y0>85</y0><y1>411</y1></column><column><dont_care>False</dont_care><x0>139</x0><x1>431</x1><y0>63</y0><y1>85</y1></column><column><dont_care>False</dont_care><x0>227</x0><x1>292</x1><y0>25</y0><y1>63</y1></column><column><dont_care>False</dont_care><x0>227</x0><x1>292</x1><y0>85</y0><y1>411</y1></column><column><dont_care>False</dont_care><x0>292</x0><x1>372</x1><y0>25</y0><y1>63</y1></column><column><dont_care>False</dont_care><x0>292</x0><x1>372</x1><y0>85</y0><y1>411</y1></column><column><dont_care>False</dont_care><x0>372</x0><x1>431</x1><y0>25</y0><y1>63</y1></column><column><dont_care>False</dont_care><x0>372</x0><x1>431</x1><y0>85</y0><y1>411</y1></column><column><dont_care>False</dont_care><x0>431</x0><x1>505</x1><y0>25</y0><y1>63</y1></column><column><dont_care>False</dont_care><x0>431</x0><x1>505</x1><y0>85</y0><y1>411</y1></column><column><dont_care>False</dont_care><x0>431</x0><x1>690</x1><y0>63</y0><y1>85</y1></column><column><dont_care>False</dont_care><x0>505</x0><x1>572</x1><y0>25</y0><y1>63</y1></column><column><dont_care>False</dont_care><x0>505</x0><x1>572</x1><y0>85</y0><y1>411</y1></column><column><dont_care>False</dont_care><x0>572</x0><x1>640</x1><y0>25</y0><y1>63</y1></column><column><dont_care>False</dont_care><x0>572</x0><x1>640</x1><y0>85</y0><y1>411</y1></column><column><dont_care>False</dont_care><x0>640</x0><x1>690</x1><y0>25</y0><y1>63</y1></column><column><dont_care>False</dont_care><x0>640</x0><x1>690</x1><y0>85</y0><y1>411</y1></column></columns></object></annotation>