<annotation><folder>images</folder><filename>ar_ge_2016_eng_73_2.jpg</filename><path>all_images/ar_ge_2016_eng_73_2.jpg</path><source><database>Unknown</database></source><size><width>840</width><height>195</height><depth>3</depth></size><segmentated>0</segmentated><object><name>table</name><pose>Unspecified</pose><truncated>0</truncated><difficult>0</difficult><bndbox><xmin>0</xmin><ymin>0</ymin><xmax>840</xmax><ymax>195</ymax></bndbox><columns><column><dont_care>False</dont_care><x0>17</x0><x1>184</x1><y0>10</y0><y1>182</y1></column><column><dont_care>False</dont_care><x0>184</x0><x1>263</x1><y0>10</y0><y1>182</y1></column><column><dont_care>False</dont_care><x0>263</x0><x1>342</x1><y0>10</y0><y1>182</y1></column><column><dont_care>False</dont_care><x0>342</x0><x1>425</x1><y0>10</y0><y1>182</y1></column><column><dont_care>False</dont_care><x0>425</x0><x1>501</x1><y0>10</y0><y1>182</y1></column><column><dont_care>False</dont_care><x0>501</x0><x1>649</x1><y0>10</y0><y1>182</y1></column><column><dont_care>False</dont_care><x0>649</x0><x1>820</x1><y0>10</y0><y1>182</y1></column></columns></object></annotation>