<annotation><folder>images</folder><filename>ar_alstom_2010_eng_81_0.jpg</filename><path>all_images/ar_alstom_2010_eng_81_0.jpg</path><source><database>Unknown</database></source><size><width>706</width><height>476</height><depth>3</depth></size><segmentated>0</segmentated><object><name>table</name><pose>Unspecified</pose><truncated>0</truncated><difficult>0</difficult><bndbox><xmin>0</xmin><ymin>0</ymin><xmax>706</xmax><ymax>476</ymax></bndbox><rows><row><dont_care>False</dont_care><x0>11</x0><x1>693</x1><y0>33</y0><y1>66</y1></row><row><dont_care>False</dont_care><x0>11</x0><x1>693</x1><y0>66</y0><y1>90</y1></row><row><dont_care>False</dont_care><x0>11</x0><x1>693</x1><y0>90</y0><y1>104</y1></row><row><dont_care>False</dont_care><x0>11</x0><x1>693</x1><y0>104</y0><y1>120</y1></row><row><dont_care>False</dont_care><x0>11</x0><x1>693</x1><y0>120</y0><y1>134</y1></row><row><dont_care>False</dont_care><x0>11</x0><x1>693</x1><y0>134</y0><y1>152</y1></row><row><dont_care>False</dont_care><x0>11</x0><x1>693</x1><y0>152</y0><y1>172</y1></row><row><dont_care>False</dont_care><x0>11</x0><x1>693</x1><y0>172</y0><y1>185</y1></row><row><dont_care>False</dont_care><x0>11</x0><x1>693</x1><y0>185</y0><y1>201</y1></row><row><dont_care>False</dont_care><x0>11</x0><x1>693</x1><y0>201</y0><y1>223</y1></row><row><dont_care>False</dont_care><x0>11</x0><x1>693</x1><y0>223</y0><y1>241</y1></row><row><dont_care>False</dont_care><x0>11</x0><x1>693</x1><y0>241</y0><y1>254</y1></row><row><dont_care>False</dont_care><x0>11</x0><x1>693</x1><y0>254</y0><y1>272</y1></row><row><dont_care>False</dont_care><x0>11</x0><x1>693</x1><y0>272</y0><y1>291</y1></row><row><dont_care>False</dont_care><x0>11</x0><x1>693</x1><y0>291</y0><y1>310</y1></row><row><dont_care>False</dont_care><x0>11</x0><x1>693</x1><y0>310</y0><y1>329</y1></row><row><dont_care>False</dont_care><x0>11</x0><x1>693</x1><y0>329</y0><y1>341</y1></row><row><dont_care>False</dont_care><x0>11</x0><x1>693</x1><y0>341</y0><y1>360</y1></row><row><dont_care>False</dont_care><x0>11</x0><x1>693</x1><y0>360</y0><y1>376</y1></row><row><dont_care>False</dont_care><x0>11</x0><x1>693</x1><y0>376</y0><y1>389</y1></row><row><dont_care>False</dont_care><x0>11</x0><x1>693</x1><y0>389</y0><y1>411</y1></row><row><dont_care>False</dont_care><x0>11</x0><x1>693</x1><y0>411</y0><y1>428</y1></row><row><dont_care>False</dont_care><x0>11</x0><x1>693</x1><y0>428</y0><y1>448</y1></row><row><dont_care>False</dont_care><x0>11</x0><x1>693</x1><y0>448</y0><y1>463</y1></row></rows></object></annotation>