<annotation><folder>images</folder><filename>ar_alstom_2015_noneng_47_1.jpg</filename><path>all_images/ar_alstom_2015_noneng_47_1.jpg</path><source><database>Unknown</database></source><size><width>716</width><height>285</height><depth>3</depth></size><segmentated>0</segmentated><object><name>table</name><pose>Unspecified</pose><truncated>0</truncated><difficult>0</difficult><bndbox><xmin>0</xmin><ymin>0</ymin><xmax>716</xmax><ymax>285</ymax></bndbox><rows><row><dont_care>False</dont_care><x0>16</x0><x1>236</x1><y0>15</y0><y1>67</y1></row><row><dont_care>False</dont_care><x0>16</x0><x1>692</x1><y0>67</y0><y1>84</y1></row><row><dont_care>False</dont_care><x0>16</x0><x1>692</x1><y0>84</y0><y1>105</y1></row><row><dont_care>False</dont_care><x0>16</x0><x1>692</x1><y0>105</y0><y1>121</y1></row><row><dont_care>False</dont_care><x0>16</x0><x1>692</x1><y0>121</y0><y1>152</y1></row><row><dont_care>False</dont_care><x0>16</x0><x1>692</x1><y0>152</y0><y1>170</y1></row><row><dont_care>False</dont_care><x0>16</x0><x1>692</x1><y0>170</y0><y1>202</y1></row><row><dont_care>False</dont_care><x0>16</x0><x1>692</x1><y0>202</y0><y1>220</y1></row><row><dont_care>False</dont_care><x0>16</x0><x1>692</x1><y0>220</y0><y1>237</y1></row><row><dont_care>False</dont_care><x0>16</x0><x1>692</x1><y0>237</y0><y1>270</y1></row><row><dont_care>False</dont_care><x0>236</x0><x1>692</x1><y0>15</y0><y1>33</y1></row><row><dont_care>False</dont_care><x0>236</x0><x1>692</x1><y0>33</y0><y1>67</y1></row></rows></object></annotation>