<annotation><folder>images</folder><filename>ar_alstom_2013_eng_14_0.jpg</filename><path>all_images/ar_alstom_2013_eng_14_0.jpg</path><source><database>Unknown</database></source><size><width>734</width><height>846</height><depth>3</depth></size><segmentated>0</segmentated><object><name>table</name><pose>Unspecified</pose><truncated>0</truncated><difficult>0</difficult><bndbox><xmin>0</xmin><ymin>0</ymin><xmax>734</xmax><ymax>846</ymax></bndbox><rows><row><dont_care>False</dont_care><x0>15</x0><x1>697</x1><y0>20</y0><y1>51</y1></row><row><dont_care>False</dont_care><x0>15</x0><x1>697</x1><y0>51</y0><y1>69</y1></row><row><dont_care>False</dont_care><x0>15</x0><x1>697</x1><y0>69</y0><y1>106</y1></row><row><dont_care>False</dont_care><x0>15</x0><x1>697</x1><y0>106</y0><y1>135</y1></row><row><dont_care>False</dont_care><x0>15</x0><x1>697</x1><y0>135</y0><y1>169</y1></row><row><dont_care>False</dont_care><x0>15</x0><x1>697</x1><y0>169</y0><y1>186</y1></row><row><dont_care>False</dont_care><x0>15</x0><x1>697</x1><y0>186</y0><y1>204</y1></row><row><dont_care>False</dont_care><x0>15</x0><x1>697</x1><y0>204</y0><y1>221</y1></row><row><dont_care>False</dont_care><x0>15</x0><x1>697</x1><y0>221</y0><y1>236</y1></row><row><dont_care>False</dont_care><x0>15</x0><x1>697</x1><y0>236</y0><y1>271</y1></row><row><dont_care>False</dont_care><x0>15</x0><x1>697</x1><y0>271</y0><y1>290</y1></row><row><dont_care>False</dont_care><x0>15</x0><x1>697</x1><y0>290</y0><y1>307</y1></row><row><dont_care>False</dont_care><x0>15</x0><x1>697</x1><y0>307</y0><y1>326</y1></row><row><dont_care>False</dont_care><x0>15</x0><x1>697</x1><y0>326</y0><y1>342</y1></row><row><dont_care>False</dont_care><x0>15</x0><x1>697</x1><y0>342</y0><y1>360</y1></row><row><dont_care>False</dont_care><x0>15</x0><x1>697</x1><y0>360</y0><y1>375</y1></row><row><dont_care>False</dont_care><x0>15</x0><x1>697</x1><y0>375</y0><y1>394</y1></row><row><dont_care>False</dont_care><x0>15</x0><x1>697</x1><y0>394</y0><y1>411</y1></row><row><dont_care>False</dont_care><x0>15</x0><x1>697</x1><y0>411</y0><y1>430</y1></row><row><dont_care>False</dont_care><x0>15</x0><x1>697</x1><y0>430</y0><y1>445</y1></row><row><dont_care>False</dont_care><x0>15</x0><x1>697</x1><y0>445</y0><y1>463</y1></row><row><dont_care>False</dont_care><x0>15</x0><x1>697</x1><y0>463</y0><y1>477</y1></row><row><dont_care>False</dont_care><x0>15</x0><x1>697</x1><y0>477</y0><y1>497</y1></row><row><dont_care>False</dont_care><x0>15</x0><x1>697</x1><y0>497</y0><y1>515</y1></row><row><dont_care>False</dont_care><x0>15</x0><x1>697</x1><y0>515</y0><y1>535</y1></row><row><dont_care>False</dont_care><x0>15</x0><x1>697</x1><y0>535</y0><y1>551</y1></row><row><dont_care>False</dont_care><x0>15</x0><x1>697</x1><y0>551</y0><y1>565</y1></row><row><dont_care>False</dont_care><x0>15</x0><x1>697</x1><y0>565</y0><y1>583</y1></row><row><dont_care>False</dont_care><x0>15</x0><x1>697</x1><y0>583</y0><y1>601</y1></row><row><dont_care>False</dont_care><x0>15</x0><x1>697</x1><y0>601</y0><y1>617</y1></row><row><dont_care>False</dont_care><x0>15</x0><x1>697</x1><y0>617</y0><y1>635</y1></row><row><dont_care>False</dont_care><x0>15</x0><x1>697</x1><y0>635</y0><y1>652</y1></row><row><dont_care>False</dont_care><x0>15</x0><x1>697</x1><y0>652</y0><y1>670</y1></row><row><dont_care>False</dont_care><x0>15</x0><x1>697</x1><y0>670</y0><y1>689</y1></row><row><dont_care>False</dont_care><x0>15</x0><x1>697</x1><y0>689</y0><y1>703</y1></row><row><dont_care>False</dont_care><x0>15</x0><x1>697</x1><y0>703</y0><y1>724</y1></row><row><dont_care>False</dont_care><x0>15</x0><x1>697</x1><y0>724</y0><y1>742</y1></row><row><dont_care>False</dont_care><x0>15</x0><x1>697</x1><y0>742</y0><y1>757</y1></row><row><dont_care>False</dont_care><x0>15</x0><x1>697</x1><y0>757</y0><y1>774</y1></row><row><dont_care>False</dont_care><x0>15</x0><x1>697</x1><y0>774</y0><y1>792</y1></row><row><dont_care>False</dont_care><x0>15</x0><x1>697</x1><y0>792</y0><y1>825</y1></row></rows></object></annotation>