<annotation><folder>images</folder><filename>ar_alstom_2016_eng_50_0.jpg</filename><path>all_images/ar_alstom_2016_eng_50_0.jpg</path><source><database>Unknown</database></source><size><width>702</width><height>282</height><depth>3</depth></size><segmentated>0</segmentated><object><name>table</name><pose>Unspecified</pose><truncated>0</truncated><difficult>0</difficult><bndbox><xmin>0</xmin><ymin>0</ymin><xmax>702</xmax><ymax>282</ymax></bndbox><rows><row><dont_care>False</dont_care><x0>15</x0><x1>485</x1><y0>12</y0><y1>46</y1></row><row><dont_care>False</dont_care><x0>15</x0><x1>689</x1><y0>46</y0><y1>64</y1></row><row><dont_care>False</dont_care><x0>15</x0><x1>689</x1><y0>64</y0><y1>79</y1></row><row><dont_care>False</dont_care><x0>15</x0><x1>689</x1><y0>79</y0><y1>98</y1></row><row><dont_care>False</dont_care><x0>15</x0><x1>689</x1><y0>98</y0><y1>115</y1></row><row><dont_care>False</dont_care><x0>15</x0><x1>689</x1><y0>115</y0><y1>132</y1></row><row><dont_care>False</dont_care><x0>15</x0><x1>689</x1><y0>132</y0><y1>151</y1></row><row><dont_care>False</dont_care><x0>15</x0><x1>689</x1><y0>151</y0><y1>168</y1></row><row><dont_care>False</dont_care><x0>15</x0><x1>689</x1><y0>168</y0><y1>184</y1></row><row><dont_care>False</dont_care><x0>15</x0><x1>689</x1><y0>184</y0><y1>202</y1></row><row><dont_care>False</dont_care><x0>15</x0><x1>689</x1><y0>202</y0><y1>220</y1></row><row><dont_care>False</dont_care><x0>15</x0><x1>689</x1><y0>220</y0><y1>237</y1></row><row><dont_care>False</dont_care><x0>15</x0><x1>689</x1><y0>237</y0><y1>255</y1></row><row><dont_care>False</dont_care><x0>15</x0><x1>689</x1><y0>255</y0><y1>270</y1></row><row><dont_care>False</dont_care><x0>485</x0><x1>689</x1><y0>12</y0><y1>25</y1></row><row><dont_care>False</dont_care><x0>485</x0><x1>689</x1><y0>25</y0><y1>46</y1></row></rows></object></annotation>