<annotation><folder>images</folder><filename>ar_bmw_2010_eng_34_0.jpg</filename><path>all_images/ar_bmw_2010_eng_34_0.jpg</path><source><database>Unknown</database></source><size><width>670</width><height>461</height><depth>3</depth></size><segmentated>0</segmentated><object><name>table</name><pose>Unspecified</pose><truncated>0</truncated><difficult>0</difficult><bndbox><xmin>0</xmin><ymin>0</ymin><xmax>670</xmax><ymax>461</ymax></bndbox><rows><row><dont_care>False</dont_care><x0>15</x0><x1>657</x1><y0>18</y0><y1>34</y1></row><row><dont_care>False</dont_care><x0>15</x0><x1>657</x1><y0>34</y0><y1>87</y1></row><row><dont_care>False</dont_care><x0>15</x0><x1>657</x1><y0>87</y0><y1>109</y1></row><row><dont_care>False</dont_care><x0>15</x0><x1>657</x1><y0>109</y0><y1>126</y1></row><row><dont_care>False</dont_care><x0>15</x0><x1>657</x1><y0>126</y0><y1>143</y1></row><row><dont_care>False</dont_care><x0>15</x0><x1>657</x1><y0>143</y0><y1>161</y1></row><row><dont_care>False</dont_care><x0>15</x0><x1>657</x1><y0>161</y0><y1>183</y1></row><row><dont_care>False</dont_care><x0>15</x0><x1>657</x1><y0>183</y0><y1>209</y1></row><row><dont_care>False</dont_care><x0>15</x0><x1>657</x1><y0>209</y0><y1>227</y1></row><row><dont_care>False</dont_care><x0>15</x0><x1>657</x1><y0>227</y0><y1>245</y1></row><row><dont_care>False</dont_care><x0>15</x0><x1>657</x1><y0>245</y0><y1>271</y1></row><row><dont_care>False</dont_care><x0>15</x0><x1>657</x1><y0>271</y0><y1>288</y1></row><row><dont_care>False</dont_care><x0>15</x0><x1>657</x1><y0>288</y0><y1>310</y1></row><row><dont_care>False</dont_care><x0>15</x0><x1>657</x1><y0>310</y0><y1>337</y1></row><row><dont_care>False</dont_care><x0>15</x0><x1>657</x1><y0>337</y0><y1>353</y1></row><row><dont_care>False</dont_care><x0>15</x0><x1>657</x1><y0>353</y0><y1>370</y1></row><row><dont_care>False</dont_care><x0>15</x0><x1>657</x1><y0>370</y0><y1>383</y1></row><row><dont_care>False</dont_care><x0>15</x0><x1>657</x1><y0>383</y0><y1>401</y1></row><row><dont_care>False</dont_care><x0>15</x0><x1>657</x1><y0>401</y0><y1>416</y1></row><row><dont_care>False</dont_care><x0>15</x0><x1>657</x1><y0>416</y0><y1>434</y1></row><row><dont_care>False</dont_care><x0>15</x0><x1>657</x1><y0>434</y0><y1>456</y1></row></rows></object></annotation>