<annotation><folder>images</folder><filename>ar_basf_2009_noneng_37_0.jpg</filename><path>all_images/ar_basf_2009_noneng_37_0.jpg</path><source><database>Unknown</database></source><size><width>695</width><height>278</height><depth>3</depth></size><segmentated>0</segmentated><object><name>table</name><pose>Unspecified</pose><truncated>0</truncated><difficult>0</difficult><bndbox><xmin>0</xmin><ymin>0</ymin><xmax>695</xmax><ymax>278</ymax></bndbox><rows><row><dont_care>False</dont_care><x0>13</x0><x1>685</x1><y0>11</y0><y1>35</y1></row><row><dont_care>False</dont_care><x0>13</x0><x1>685</x1><y0>35</y0><y1>70</y1></row><row><dont_care>False</dont_care><x0>13</x0><x1>685</x1><y0>70</y0><y1>85</y1></row><row><dont_care>False</dont_care><x0>13</x0><x1>685</x1><y0>85</y0><y1>102</y1></row><row><dont_care>False</dont_care><x0>13</x0><x1>685</x1><y0>102</y0><y1>118</y1></row><row><dont_care>False</dont_care><x0>13</x0><x1>685</x1><y0>118</y0><y1>135</y1></row><row><dont_care>False</dont_care><x0>13</x0><x1>685</x1><y0>135</y0><y1>152</y1></row><row><dont_care>False</dont_care><x0>13</x0><x1>685</x1><y0>152</y0><y1>169</y1></row><row><dont_care>False</dont_care><x0>13</x0><x1>685</x1><y0>169</y0><y1>186</y1></row><row><dont_care>False</dont_care><x0>13</x0><x1>685</x1><y0>186</y0><y1>200</y1></row><row><dont_care>False</dont_care><x0>13</x0><x1>685</x1><y0>200</y0><y1>218</y1></row><row><dont_care>False</dont_care><x0>13</x0><x1>685</x1><y0>218</y0><y1>235</y1></row><row><dont_care>False</dont_care><x0>13</x0><x1>685</x1><y0>235</y0><y1>249</y1></row><row><dont_care>False</dont_care><x0>13</x0><x1>685</x1><y0>249</y0><y1>266</y1></row></rows></object></annotation>