<annotation><folder>images</folder><filename>ar_bmw_2010_eng_6_2.jpg</filename><path>all_images/ar_bmw_2010_eng_6_2.jpg</path><source><database>Unknown</database></source><size><width>669</width><height>240</height><depth>3</depth></size><segmentated>0</segmentated><object><name>table</name><pose>Unspecified</pose><truncated>0</truncated><difficult>0</difficult><bndbox><xmin>0</xmin><ymin>0</ymin><xmax>669</xmax><ymax>240</ymax></bndbox><rows><row><dont_care>False</dont_care><x0>17</x0><x1>657</x1><y0>11</y0><y1>29</y1></row><row><dont_care>False</dont_care><x0>17</x0><x1>657</x1><y0>29</y0><y1>45</y1></row><row><dont_care>False</dont_care><x0>17</x0><x1>657</x1><y0>45</y0><y1>60</y1></row><row><dont_care>False</dont_care><x0>17</x0><x1>657</x1><y0>60</y0><y1>90</y1></row><row><dont_care>False</dont_care><x0>17</x0><x1>657</x1><y0>90</y0><y1>106</y1></row><row><dont_care>False</dont_care><x0>17</x0><x1>657</x1><y0>106</y0><y1>122</y1></row><row><dont_care>False</dont_care><x0>17</x0><x1>657</x1><y0>122</y0><y1>137</y1></row><row><dont_care>False</dont_care><x0>17</x0><x1>657</x1><y0>137</y0><y1>152</y1></row><row><dont_care>False</dont_care><x0>17</x0><x1>657</x1><y0>152</y0><y1>168</y1></row><row><dont_care>False</dont_care><x0>17</x0><x1>657</x1><y0>168</y0><y1>186</y1></row><row><dont_care>False</dont_care><x0>17</x0><x1>657</x1><y0>186</y0><y1>200</y1></row><row><dont_care>False</dont_care><x0>17</x0><x1>657</x1><y0>200</y0><y1>222</y1></row></rows></object></annotation>