<annotation><folder>images</folder><filename>ar_basf_2011_noneng_19_0.jpg</filename><path>all_images/ar_basf_2011_noneng_19_0.jpg</path><source><database>Unknown</database></source><size><width>695</width><height>247</height><depth>3</depth></size><segmentated>0</segmentated><object><name>table</name><pose>Unspecified</pose><truncated>0</truncated><difficult>0</difficult><bndbox><xmin>0</xmin><ymin>0</ymin><xmax>695</xmax><ymax>247</ymax></bndbox><rows><row><dont_care>False</dont_care><x0>13</x0><x1>680</x1><y0>36</y0><y1>86</y1></row><row><dont_care>False</dont_care><x0>13</x0><x1>680</x1><y0>86</y0><y1>102</y1></row><row><dont_care>False</dont_care><x0>13</x0><x1>680</x1><y0>102</y0><y1>119</y1></row><row><dont_care>False</dont_care><x0>13</x0><x1>680</x1><y0>119</y0><y1>137</y1></row><row><dont_care>False</dont_care><x0>13</x0><x1>680</x1><y0>137</y0><y1>153</y1></row><row><dont_care>False</dont_care><x0>13</x0><x1>680</x1><y0>153</y0><y1>170</y1></row><row><dont_care>False</dont_care><x0>13</x0><x1>680</x1><y0>170</y0><y1>187</y1></row><row><dont_care>False</dont_care><x0>13</x0><x1>680</x1><y0>187</y0><y1>201</y1></row><row><dont_care>False</dont_care><x0>13</x0><x1>680</x1><y0>201</y0><y1>219</y1></row><row><dont_care>False</dont_care><x0>13</x0><x1>680</x1><y0>219</y0><y1>236</y1></row></rows></object></annotation>