<annotation><folder>images</folder><filename>ar_basf_2011_noneng_1_0.jpg</filename><path>all_images/ar_basf_2011_noneng_1_0.jpg</path><source><database>Unknown</database></source><size><width>698</width><height>432</height><depth>3</depth></size><segmentated>0</segmentated><object><name>table</name><pose>Unspecified</pose><truncated>0</truncated><difficult>0</difficult><bndbox><xmin>0</xmin><ymin>0</ymin><xmax>698</xmax><ymax>432</ymax></bndbox><rows><row><dont_care>False</dont_care><x0>12</x0><x1>684</x1><y0>39</y0><y1>105</y1></row><row><dont_care>False</dont_care><x0>12</x0><x1>684</x1><y0>105</y0><y1>122</y1></row><row><dont_care>False</dont_care><x0>12</x0><x1>684</x1><y0>122</y0><y1>139</y1></row><row><dont_care>False</dont_care><x0>12</x0><x1>684</x1><y0>139</y0><y1>155</y1></row><row><dont_care>False</dont_care><x0>12</x0><x1>684</x1><y0>155</y0><y1>172</y1></row><row><dont_care>False</dont_care><x0>12</x0><x1>684</x1><y0>172</y0><y1>187</y1></row><row><dont_care>False</dont_care><x0>12</x0><x1>684</x1><y0>187</y0><y1>204</y1></row><row><dont_care>False</dont_care><x0>12</x0><x1>684</x1><y0>204</y0><y1>221</y1></row><row><dont_care>False</dont_care><x0>12</x0><x1>684</x1><y0>221</y0><y1>238</y1></row><row><dont_care>False</dont_care><x0>12</x0><x1>684</x1><y0>238</y0><y1>254</y1></row><row><dont_care>False</dont_care><x0>12</x0><x1>684</x1><y0>254</y0><y1>271</y1></row><row><dont_care>False</dont_care><x0>12</x0><x1>684</x1><y0>271</y0><y1>286</y1></row><row><dont_care>False</dont_care><x0>12</x0><x1>684</x1><y0>286</y0><y1>303</y1></row><row><dont_care>False</dont_care><x0>12</x0><x1>684</x1><y0>303</y0><y1>319</y1></row><row><dont_care>False</dont_care><x0>12</x0><x1>684</x1><y0>319</y0><y1>336</y1></row><row><dont_care>False</dont_care><x0>12</x0><x1>684</x1><y0>336</y0><y1>351</y1></row><row><dont_care>False</dont_care><x0>12</x0><x1>684</x1><y0>351</y0><y1>369</y1></row><row><dont_care>False</dont_care><x0>12</x0><x1>684</x1><y0>369</y0><y1>384</y1></row><row><dont_care>False</dont_care><x0>12</x0><x1>684</x1><y0>384</y0><y1>402</y1></row><row><dont_care>False</dont_care><x0>12</x0><x1>684</x1><y0>402</y0><y1>418</y1></row></rows></object></annotation>