<annotation><folder>images</folder><filename>ar_bouygues_2015_noneng_23_0.jpg</filename><path>all_images/ar_bouygues_2015_noneng_23_0.jpg</path><source><database>Unknown</database></source><size><width>691</width><height>799</height><depth>3</depth></size><segmentated>0</segmentated><object><name>table</name><pose>Unspecified</pose><truncated>0</truncated><difficult>0</difficult><bndbox><xmin>0</xmin><ymin>0</ymin><xmax>691</xmax><ymax>799</ymax></bndbox><rows><row><dont_care>False</dont_care><x0>14</x0><x1>677</x1><y0>68</y0><y1>99</y1></row><row><dont_care>False</dont_care><x0>14</x0><x1>499</x1><y0>99</y0><y1>181</y1></row><row><dont_care>False</dont_care><x0>14</x0><x1>677</x1><y0>181</y0><y1>196</y1></row><row><dont_care>False</dont_care><x0>14</x0><x1>677</x1><y0>196</y0><y1>220</y1></row><row><dont_care>False</dont_care><x0>14</x0><x1>677</x1><y0>220</y0><y1>240</y1></row><row><dont_care>False</dont_care><x0>14</x0><x1>677</x1><y0>240</y0><y1>259</y1></row><row><dont_care>False</dont_care><x0>14</x0><x1>677</x1><y0>259</y0><y1>278</y1></row><row><dont_care>False</dont_care><x0>14</x0><x1>677</x1><y0>278</y0><y1>295</y1></row><row><dont_care>False</dont_care><x0>14</x0><x1>677</x1><y0>295</y0><y1>311</y1></row><row><dont_care>False</dont_care><x0>14</x0><x1>677</x1><y0>311</y0><y1>331</y1></row><row><dont_care>False</dont_care><x0>14</x0><x1>677</x1><y0>331</y0><y1>350</y1></row><row><dont_care>False</dont_care><x0>14</x0><x1>677</x1><y0>350</y0><y1>367</y1></row><row><dont_care>False</dont_care><x0>14</x0><x1>677</x1><y0>367</y0><y1>386</y1></row><row><dont_care>False</dont_care><x0>14</x0><x1>677</x1><y0>386</y0><y1>410</y1></row><row><dont_care>False</dont_care><x0>14</x0><x1>677</x1><y0>410</y0><y1>429</y1></row><row><dont_care>False</dont_care><x0>14</x0><x1>677</x1><y0>429</y0><y1>450</y1></row><row><dont_care>False</dont_care><x0>14</x0><x1>677</x1><y0>450</y0><y1>468</y1></row><row><dont_care>False</dont_care><x0>14</x0><x1>677</x1><y0>468</y0><y1>495</y1></row><row><dont_care>False</dont_care><x0>14</x0><x1>677</x1><y0>495</y0><y1>516</y1></row><row><dont_care>False</dont_care><x0>14</x0><x1>677</x1><y0>516</y0><y1>533</y1></row><row><dont_care>False</dont_care><x0>14</x0><x1>677</x1><y0>533</y0><y1>556</y1></row><row><dont_care>False</dont_care><x0>14</x0><x1>677</x1><y0>556</y0><y1>575</y1></row><row><dont_care>False</dont_care><x0>14</x0><x1>677</x1><y0>575</y0><y1>589</y1></row><row><dont_care>False</dont_care><x0>14</x0><x1>677</x1><y0>589</y0><y1>613</y1></row><row><dont_care>False</dont_care><x0>14</x0><x1>677</x1><y0>613</y0><y1>630</y1></row><row><dont_care>False</dont_care><x0>14</x0><x1>677</x1><y0>630</y0><y1>655</y1></row><row><dont_care>False</dont_care><x0>14</x0><x1>677</x1><y0>655</y0><y1>676</y1></row><row><dont_care>False</dont_care><x0>14</x0><x1>677</x1><y0>676</y0><y1>708</y1></row><row><dont_care>False</dont_care><x0>14</x0><x1>677</x1><y0>708</y0><y1>733</y1></row><row><dont_care>False</dont_care><x0>14</x0><x1>677</x1><y0>733</y0><y1>752</y1></row><row><dont_care>False</dont_care><x0>14</x0><x1>677</x1><y0>752</y0><y1>783</y1></row><row><dont_care>False</dont_care><x0>499</x0><x1>677</x1><y0>99</y0><y1>136</y1></row><row><dont_care>False</dont_care><x0>499</x0><x1>677</x1><y0>136</y0><y1>181</y1></row></rows></object></annotation>