<annotation><folder>images</folder><filename>ar_basf_2011_noneng_96_0.jpg</filename><path>all_images/ar_basf_2011_noneng_96_0.jpg</path><source><database>Unknown</database></source><size><width>701</width><height>270</height><depth>1</depth></size><segmentated>0</segmentated><object><name>table</name><pose>Unspecified</pose><truncated>0</truncated><difficult>0</difficult><bndbox><xmin>0</xmin><ymin>0</ymin><xmax>701</xmax><ymax>270</ymax></bndbox><rows><row><dont_care>False</dont_care><x0>12</x0><x1>683</x1><y0>36</y0><y1>51</y1></row><row><dont_care>False</dont_care><x0>12</x0><x1>683</x1><y0>51</y0><y1>67</y1></row><row><dont_care>False</dont_care><x0>12</x0><x1>683</x1><y0>67</y0><y1>176</y1></row><row><dont_care>False</dont_care><x0>12</x0><x1>683</x1><y0>176</y0><y1>261</y1></row></rows></object></annotation>