<annotation><folder>images</folder><filename>ar_citi_2018_eng_27_0.jpg</filename><path>all_images/ar_citi_2018_eng_27_0.jpg</path><source><database>Unknown</database></source><size><width>750</width><height>291</height><depth>1</depth></size><segmentated>0</segmentated><object><name>table</name><pose>Unspecified</pose><truncated>0</truncated><difficult>0</difficult><bndbox><xmin>0</xmin><ymin>0</ymin><xmax>750</xmax><ymax>291</ymax></bndbox><rows><row><dont_care>False</dont_care><x0>15</x0><x1>729</x1><y0>18</y0><y1>47</y1></row><row><dont_care>False</dont_care><x0>15</x0><x1>729</x1><y0>47</y0><y1>67</y1></row><row><dont_care>False</dont_care><x0>15</x0><x1>729</x1><y0>67</y0><y1>79</y1></row><row><dont_care>False</dont_care><x0>15</x0><x1>729</x1><y0>79</y0><y1>95</y1></row><row><dont_care>False</dont_care><x0>15</x0><x1>729</x1><y0>95</y0><y1>115</y1></row><row><dont_care>False</dont_care><x0>15</x0><x1>729</x1><y0>115</y0><y1>130</y1></row><row><dont_care>False</dont_care><x0>15</x0><x1>729</x1><y0>130</y0><y1>143</y1></row><row><dont_care>False</dont_care><x0>15</x0><x1>729</x1><y0>143</y0><y1>158</y1></row><row><dont_care>False</dont_care><x0>15</x0><x1>729</x1><y0>158</y0><y1>171</y1></row><row><dont_care>False</dont_care><x0>15</x0><x1>729</x1><y0>171</y0><y1>193</y1></row><row><dont_care>False</dont_care><x0>15</x0><x1>729</x1><y0>193</y0><y1>214</y1></row><row><dont_care>False</dont_care><x0>15</x0><x1>729</x1><y0>214</y0><y1>235</y1></row><row><dont_care>False</dont_care><x0>15</x0><x1>729</x1><y0>235</y0><y1>257</y1></row><row><dont_care>False</dont_care><x0>15</x0><x1>729</x1><y0>257</y0><y1>276</y1></row></rows></object></annotation>