<annotation><folder>images</folder><filename>ar_deutschebank_2008_noneng_138_0.jpg</filename><path>all_images/ar_deutschebank_2008_noneng_138_0.jpg</path><source><database>Unknown</database></source><size><width>661</width><height>336</height><depth>3</depth></size><segmentated>0</segmentated><object><name>table</name><pose>Unspecified</pose><truncated>0</truncated><difficult>0</difficult><bndbox><xmin>0</xmin><ymin>0</ymin><xmax>661</xmax><ymax>336</ymax></bndbox><rows><row><dont_care>False</dont_care><x0>22</x0><x1>639</x1><y0>41</y0><y1>54</y1></row><row><dont_care>False</dont_care><x0>22</x0><x1>639</x1><y0>54</y0><y1>68</y1></row><row><dont_care>False</dont_care><x0>22</x0><x1>639</x1><y0>68</y0><y1>81</y1></row><row><dont_care>False</dont_care><x0>22</x0><x1>639</x1><y0>81</y0><y1>108</y1></row><row><dont_care>False</dont_care><x0>22</x0><x1>639</x1><y0>108</y0><y1>123</y1></row><row><dont_care>False</dont_care><x0>22</x0><x1>639</x1><y0>123</y0><y1>164</y1></row><row><dont_care>False</dont_care><x0>22</x0><x1>639</x1><y0>164</y0><y1>207</y1></row><row><dont_care>False</dont_care><x0>22</x0><x1>639</x1><y0>207</y0><y1>220</y1></row><row><dont_care>False</dont_care><x0>22</x0><x1>639</x1><y0>220</y0><y1>234</y1></row><row><dont_care>False</dont_care><x0>22</x0><x1>639</x1><y0>234</y0><y1>248</y1></row><row><dont_care>False</dont_care><x0>22</x0><x1>639</x1><y0>248</y0><y1>262</y1></row><row><dont_care>False</dont_care><x0>22</x0><x1>639</x1><y0>262</y0><y1>276</y1></row><row><dont_care>False</dont_care><x0>22</x0><x1>639</x1><y0>276</y0><y1>289</y1></row><row><dont_care>False</dont_care><x0>22</x0><x1>639</x1><y0>289</y0><y1>303</y1></row><row><dont_care>False</dont_care><x0>22</x0><x1>639</x1><y0>303</y0><y1>317</y1></row></rows></object></annotation>