<annotation><folder>images</folder><filename>ar_enel_2015_eng_10_1.jpg</filename><path>all_images/ar_enel_2015_eng_10_1.jpg</path><source><database>Unknown</database></source><size><width>719</width><height>424</height><depth>3</depth></size><segmentated>0</segmentated><object><name>table</name><pose>Unspecified</pose><truncated>0</truncated><difficult>0</difficult><bndbox><xmin>0</xmin><ymin>0</ymin><xmax>719</xmax><ymax>424</ymax></bndbox><rows><row><dont_care>False</dont_care><x0>12</x0><x1>700</x1><y0>10</y0><y1>31</y1></row><row><dont_care>False</dont_care><x0>12</x0><x1>700</x1><y0>31</y0><y1>55</y1></row><row><dont_care>False</dont_care><x0>12</x0><x1>700</x1><y0>55</y0><y1>79</y1></row><row><dont_care>False</dont_care><x0>12</x0><x1>700</x1><y0>79</y0><y1>101</y1></row><row><dont_care>False</dont_care><x0>12</x0><x1>700</x1><y0>101</y0><y1>124</y1></row><row><dont_care>False</dont_care><x0>12</x0><x1>700</x1><y0>124</y0><y1>147</y1></row><row><dont_care>False</dont_care><x0>12</x0><x1>700</x1><y0>147</y0><y1>171</y1></row><row><dont_care>False</dont_care><x0>12</x0><x1>700</x1><y0>171</y0><y1>194</y1></row><row><dont_care>False</dont_care><x0>12</x0><x1>700</x1><y0>194</y0><y1>217</y1></row><row><dont_care>False</dont_care><x0>12</x0><x1>700</x1><y0>217</y0><y1>241</y1></row><row><dont_care>False</dont_care><x0>12</x0><x1>700</x1><y0>241</y0><y1>264</y1></row><row><dont_care>False</dont_care><x0>12</x0><x1>700</x1><y0>264</y0><y1>287</y1></row><row><dont_care>False</dont_care><x0>12</x0><x1>700</x1><y0>287</y0><y1>310</y1></row><row><dont_care>False</dont_care><x0>12</x0><x1>700</x1><y0>310</y0><y1>334</y1></row><row><dont_care>False</dont_care><x0>12</x0><x1>700</x1><y0>334</y0><y1>357</y1></row><row><dont_care>False</dont_care><x0>12</x0><x1>700</x1><y0>357</y0><y1>380</y1></row><row><dont_care>False</dont_care><x0>12</x0><x1>700</x1><y0>380</y0><y1>404</y1></row></rows></object></annotation>