<annotation><folder>images</folder><filename>ar_other_2017_eng_30_1.jpg</filename><path>all_images/ar_other_2017_eng_30_1.jpg</path><source><database>Unknown</database></source><size><width>716</width><height>352</height><depth>3</depth></size><segmentated>0</segmentated><object><name>table</name><pose>Unspecified</pose><truncated>0</truncated><difficult>0</difficult><bndbox><xmin>0</xmin><ymin>0</ymin><xmax>716</xmax><ymax>352</ymax></bndbox><rows><row><dont_care>False</dont_care><x0>15</x0><x1>697</x1><y0>20</y0><y1>49</y1></row><row><dont_care>False</dont_care><x0>15</x0><x1>697</x1><y0>49</y0><y1>71</y1></row><row><dont_care>False</dont_care><x0>15</x0><x1>697</x1><y0>71</y0><y1>90</y1></row><row><dont_care>False</dont_care><x0>15</x0><x1>697</x1><y0>90</y0><y1>111</y1></row><row><dont_care>False</dont_care><x0>15</x0><x1>697</x1><y0>111</y0><y1>132</y1></row><row><dont_care>False</dont_care><x0>15</x0><x1>697</x1><y0>132</y0><y1>154</y1></row><row><dont_care>False</dont_care><x0>15</x0><x1>697</x1><y0>154</y0><y1>175</y1></row><row><dont_care>False</dont_care><x0>15</x0><x1>697</x1><y0>175</y0><y1>196</y1></row><row><dont_care>False</dont_care><x0>15</x0><x1>697</x1><y0>196</y0><y1>227</y1></row><row><dont_care>False</dont_care><x0>15</x0><x1>697</x1><y0>227</y0><y1>247</y1></row><row><dont_care>False</dont_care><x0>15</x0><x1>697</x1><y0>247</y0><y1>268</y1></row><row><dont_care>False</dont_care><x0>15</x0><x1>697</x1><y0>268</y0><y1>290</y1></row><row><dont_care>False</dont_care><x0>15</x0><x1>697</x1><y0>290</y0><y1>312</y1></row><row><dont_care>False</dont_care><x0>15</x0><x1>697</x1><y0>312</y0><y1>333</y1></row></rows></object></annotation>