<annotation><folder>images</folder><filename>ar_siemens_2010_eng_25_0.jpg</filename><path>all_images/ar_siemens_2010_eng_25_0.jpg</path><source><database>Unknown</database></source><size><width>349</width><height>493</height><depth>3</depth></size><segmentated>0</segmentated><object><name>table</name><pose>Unspecified</pose><truncated>0</truncated><difficult>0</difficult><bndbox><xmin>0</xmin><ymin>0</ymin><xmax>349</xmax><ymax>493</ymax></bndbox><rows><row><dont_care>False</dont_care><x0>12</x0><x1>223</x1><y0>24</y0><y1>59</y1></row><row><dont_care>False</dont_care><x0>12</x0><x1>334</x1><y0>59</y0><y1>76</y1></row><row><dont_care>False</dont_care><x0>12</x0><x1>334</x1><y0>76</y0><y1>92</y1></row><row><dont_care>False</dont_care><x0>12</x0><x1>334</x1><y0>92</y0><y1>108</y1></row><row><dont_care>False</dont_care><x0>12</x0><x1>334</x1><y0>108</y0><y1>125</y1></row><row><dont_care>False</dont_care><x0>12</x0><x1>334</x1><y0>125</y0><y1>147</y1></row><row><dont_care>False</dont_care><x0>12</x0><x1>334</x1><y0>147</y0><y1>164</y1></row><row><dont_care>False</dont_care><x0>12</x0><x1>334</x1><y0>164</y0><y1>177</y1></row><row><dont_care>False</dont_care><x0>12</x0><x1>334</x1><y0>177</y0><y1>194</y1></row><row><dont_care>False</dont_care><x0>12</x0><x1>334</x1><y0>194</y0><y1>223</y1></row><row><dont_care>False</dont_care><x0>12</x0><x1>334</x1><y0>223</y0><y1>246</y1></row><row><dont_care>False</dont_care><x0>12</x0><x1>334</x1><y0>246</y0><y1>272</y1></row><row><dont_care>False</dont_care><x0>12</x0><x1>334</x1><y0>272</y0><y1>288</y1></row><row><dont_care>False</dont_care><x0>12</x0><x1>334</x1><y0>288</y0><y1>313</y1></row><row><dont_care>False</dont_care><x0>12</x0><x1>334</x1><y0>313</y0><y1>329</y1></row><row><dont_care>False</dont_care><x0>12</x0><x1>334</x1><y0>329</y0><y1>344</y1></row><row><dont_care>False</dont_care><x0>12</x0><x1>334</x1><y0>344</y0><y1>370</y1></row><row><dont_care>False</dont_care><x0>12</x0><x1>334</x1><y0>370</y0><y1>386</y1></row><row><dont_care>False</dont_care><x0>12</x0><x1>334</x1><y0>386</y0><y1>426</y1></row><row><dont_care>False</dont_care><x0>12</x0><x1>334</x1><y0>426</y0><y1>456</y1></row><row><dont_care>False</dont_care><x0>223</x0><x1>334</x1><y0>24</y0><y1>48</y1></row><row><dont_care>False</dont_care><x0>223</x0><x1>334</x1><y0>48</y0><y1>59</y1></row></rows></object></annotation>