<annotation><folder>images</folder><filename>ar_sap_2010_noneng_2_0.jpg</filename><path>all_images/ar_sap_2010_noneng_2_0.jpg</path><source><database>Unknown</database></source><size><width>763</width><height>362</height><depth>3</depth></size><segmentated>0</segmentated><object><name>table</name><pose>Unspecified</pose><truncated>0</truncated><difficult>0</difficult><bndbox><xmin>0</xmin><ymin>0</ymin><xmax>763</xmax><ymax>362</ymax></bndbox><rows><row><dont_care>False</dont_care><x0>15</x0><x1>747</x1><y0>15</y0><y1>66</y1></row><row><dont_care>False</dont_care><x0>15</x0><x1>747</x1><y0>66</y0><y1>82</y1></row><row><dont_care>False</dont_care><x0>15</x0><x1>747</x1><y0>82</y0><y1>99</y1></row><row><dont_care>False</dont_care><x0>15</x0><x1>747</x1><y0>99</y0><y1>116</y1></row><row><dont_care>False</dont_care><x0>15</x0><x1>747</x1><y0>116</y0><y1>132</y1></row><row><dont_care>False</dont_care><x0>15</x0><x1>747</x1><y0>132</y0><y1>149</y1></row><row><dont_care>False</dont_care><x0>15</x0><x1>747</x1><y0>149</y0><y1>183</y1></row><row><dont_care>False</dont_care><x0>15</x0><x1>747</x1><y0>183</y0><y1>200</y1></row><row><dont_care>False</dont_care><x0>15</x0><x1>747</x1><y0>200</y0><y1>216</y1></row><row><dont_care>False</dont_care><x0>15</x0><x1>747</x1><y0>216</y0><y1>233</y1></row><row><dont_care>False</dont_care><x0>15</x0><x1>747</x1><y0>233</y0><y1>250</y1></row><row><dont_care>False</dont_care><x0>15</x0><x1>747</x1><y0>250</y0><y1>266</y1></row><row><dont_care>False</dont_care><x0>15</x0><x1>747</x1><y0>266</y0><y1>283</y1></row><row><dont_care>False</dont_care><x0>15</x0><x1>747</x1><y0>283</y0><y1>300</y1></row><row><dont_care>False</dont_care><x0>15</x0><x1>747</x1><y0>300</y0><y1>317</y1></row><row><dont_care>False</dont_care><x0>15</x0><x1>747</x1><y0>317</y0><y1>333</y1></row><row><dont_care>False</dont_care><x0>15</x0><x1>747</x1><y0>333</y0><y1>352</y1></row></rows></object></annotation>