<annotation><folder>images</folder><filename>ar_alstom_2014_noneng_64_0.jpg</filename><path>all_images/ar_alstom_2014_noneng_64_0.jpg</path><source><database>Unknown</database></source><size><width>356</width><height>71</height><depth>3</depth></size><segmentated>0</segmentated><object><name>table</name><pose>Unspecified</pose><truncated>0</truncated><difficult>0</difficult><bndbox><xmin>0</xmin><ymin>0</ymin><xmax>356</xmax><ymax>71</ymax></bndbox><cells><tablecell><dont_care>False</dont_care><end_col>0</end_col><end_row>0</end_row><start_col>0</start_col><start_row>0</start_row><x0>13</x0><x1>138</x1><y0>18</y0><y1>37</y1></tablecell><tablecell><dont_care>False</dont_care><end_col>0</end_col><end_row>1</end_row><start_col>0</start_col><start_row>1</start_row><x0>13</x0><x1>138</x1><y0>37</y0><y1>55</y1></tablecell><tablecell><dont_care>False</dont_care><end_col>1</end_col><end_row>0</end_row><start_col>1</start_col><start_row>0</start_row><x0>138</x0><x1>227</x1><y0>18</y0><y1>37</y1></tablecell><tablecell><dont_care>False</dont_care><end_col>1</end_col><end_row>1</end_row><start_col>1</start_col><start_row>1</start_row><x0>138</x0><x1>227</x1><y0>37</y0><y1>55</y1></tablecell><tablecell><dont_care>False</dont_care><end_col>2</end_col><end_row>0</end_row><start_col>2</start_col><start_row>0</start_row><x0>227</x0><x1>337</x1><y0>18</y0><y1>37</y1></tablecell><tablecell><dont_care>False</dont_care><end_col>2</end_col><end_row>1</end_row><start_col>2</start_col><start_row>1</start_row><x0>227</x0><x1>337</x1><y0>37</y0><y1>55</y1></tablecell></cells></object></annotation>