<annotation><folder>images</folder><filename>ar_atoss_2008_noneng_28_2.jpg</filename><path>all_images/ar_atoss_2008_noneng_28_2.jpg</path><source><database>Unknown</database></source><size><width>475</width><height>80</height><depth>3</depth></size><segmentated>0</segmentated><object><name>table</name><pose>Unspecified</pose><truncated>0</truncated><difficult>0</difficult><bndbox><xmin>0</xmin><ymin>0</ymin><xmax>475</xmax><ymax>80</ymax></bndbox><cells><tablecell><dont_care>False</dont_care><end_col>0</end_col><end_row>0</end_row><start_col>0</start_col><start_row>0</start_row><x0>12</x0><x1>159</x1><y0>22</y0><y1>44</y1></tablecell><tablecell><dont_care>False</dont_care><end_col>0</end_col><end_row>1</end_row><start_col>0</start_col><start_row>1</start_row><x0>12</x0><x1>159</x1><y0>44</y0><y1>63</y1></tablecell><tablecell><dont_care>False</dont_care><end_col>1</end_col><end_row>0</end_row><start_col>1</start_col><start_row>0</start_row><x0>159</x0><x1>307</x1><y0>22</y0><y1>44</y1></tablecell><tablecell><dont_care>False</dont_care><end_col>1</end_col><end_row>1</end_row><start_col>1</start_col><start_row>1</start_row><x0>159</x0><x1>307</x1><y0>44</y0><y1>63</y1></tablecell><tablecell><dont_care>False</dont_care><end_col>2</end_col><end_row>0</end_row><start_col>2</start_col><start_row>0</start_row><x0>307</x0><x1>462</x1><y0>22</y0><y1>44</y1></tablecell><tablecell><dont_care>False</dont_care><end_col>2</end_col><end_row>1</end_row><start_col>2</start_col><start_row>1</start_row><x0>307</x0><x1>462</x1><y0>44</y0><y1>63</y1></tablecell></cells></object></annotation>