<annotation><folder>images</folder><filename>ar_box_2017_eng_34_0.jpg</filename><path>all_images/ar_box_2017_eng_34_0.jpg</path><source><database>Unknown</database></source><size><width>707</width><height>808</height><depth>1</depth></size><segmentated>0</segmentated><object><name>table</name><pose>Unspecified</pose><truncated>0</truncated><difficult>0</difficult><bndbox><xmin>0</xmin><ymin>0</ymin><xmax>707</xmax><ymax>808</ymax></bndbox><cells><tablecell><dont_care>False</dont_care><end_col>0</end_col><end_row>1</end_row><start_col>0</start_col><start_row>0</start_row><x0>30</x0><x1>497</x1><y0>12</y0><y1>45</y1></tablecell><tablecell><dont_care>False</dont_care><end_col>0</end_col><end_row>2</end_row><start_col>0</start_col><start_row>2</start_row><x0>30</x0><x1>497</x1><y0>45</y0><y1>65</y1></tablecell><tablecell><dont_care>False</dont_care><end_col>0</end_col><end_row>3</end_row><start_col>0</start_col><start_row>3</start_row><x0>30</x0><x1>497</x1><y0>65</y0><y1>77</y1></tablecell><tablecell><dont_care>False</dont_care><end_col>0</end_col><end_row>4</end_row><start_col>0</start_col><start_row>4</start_row><x0>30</x0><x1>497</x1><y0>77</y0><y1>89</y1></tablecell><tablecell><dont_care>False</dont_care><end_col>0</end_col><end_row>5</end_row><start_col>0</start_col><start_row>5</start_row><x0>30</x0><x1>497</x1><y0>89</y0><y1>100</y1></tablecell><tablecell><dont_care>False</dont_care><end_col>0</end_col><end_row>6</end_row><start_col>0</start_col><start_row>6</start_row><x0>30</x0><x1>497</x1><y0>100</y0><y1>113</y1></tablecell><tablecell><dont_care>False</dont_care><end_col>0</end_col><end_row>7</end_row><start_col>0</start_col><start_row>7</start_row><x0>30</x0><x1>497</x1><y0>113</y0><y1>125</y1></tablecell><tablecell><dont_care>False</dont_care><end_col>0</end_col><end_row>8</end_row><start_col>0</start_col><start_row>8</start_row><x0>30</x0><x1>497</x1><y0>125</y0><y1>136</y1></tablecell><tablecell><dont_care>False</dont_care><end_col>0</end_col><end_row>9</end_row><start_col>0</start_col><start_row>9</start_row><x0>30</x0><x1>497</x1><y0>136</y0><y1>148</y1></tablecell><tablecell><dont_care>False</dont_care><end_col>0</end_col><end_row>10</end_row><start_col>0</start_col><start_row>10</start_row><x0>30</x0><x1>497</x1><y0>148</y0><y1>172</y1></tablecell><tablecell><dont_care>False</dont_care><end_col>0</end_col><end_row>11</end_row><start_col>0</start_col><start_row>11</start_row><x0>30</x0><x1>497</x1><y0>172</y0><y1>183</y1></tablecell><tablecell><dont_care>False</dont_care><end_col>0</end_col><end_row>12</end_row><start_col>0</start_col><start_row>12</start_row><x0>30</x0><x1>497</x1><y0>183</y0><y1>204</y1></tablecell><tablecell><dont_care>False</dont_care><end_col>0</end_col><end_row>13</end_row><start_col>0</start_col><start_row>13</start_row><x0>30</x0><x1>497</x1><y0>204</y0><y1>219</y1></tablecell><tablecell><dont_care>False</dont_care><end_col>0</end_col><end_row>14</end_row><start_col>0</start_col><start_row>14</start_row><x0>30</x0><x1>497</x1><y0>219</y0><y1>231</y1></tablecell><tablecell><dont_care>False</dont_care><end_col>0</end_col><end_row>15</end_row><start_col>0</start_col><start_row>15</start_row><x0>30</x0><x1>497</x1><y0>231</y0><y1>256</y1></tablecell><tablecell><dont_care>False</dont_care><end_col>0</end_col><end_row>16</end_row><start_col>0</start_col><start_row>16</start_row><x0>30</x0><x1>497</x1><y0>256</y0><y1>268</y1></tablecell><tablecell><dont_care>False</dont_care><end_col>0</end_col><end_row>17</end_row><start_col>0</start_col><start_row>17</start_row><x0>30</x0><x1>497</x1><y0>268</y0><y1>283</y1></tablecell><tablecell><dont_care>False</dont_care><end_col>0</end_col><end_row>18</end_row><start_col>0</start_col><start_row>18</start_row><x0>30</x0><x1>497</x1><y0>283</y0><y1>306</y1></tablecell><tablecell><dont_care>False</dont_care><end_col>0</end_col><end_row>19</end_row><start_col>0</start_col><start_row>19</start_row><x0>30</x0><x1>497</x1><y0>306</y0><y1>318</y1></tablecell><tablecell><dont_care>False</dont_care><end_col>0</end_col><end_row>20</end_row><start_col>0</start_col><start_row>20</start_row><x0>30</x0><x1>497</x1><y0>318</y0><y1>330</y1></tablecell><tablecell><dont_care>False</dont_care><end_col>0</end_col><end_row>21</end_row><start_col>0</start_col><start_row>21</start_row><x0>30</x0><x1>497</x1><y0>330</y0><y1>341</y1></tablecell><tablecell><dont_care>False</dont_care><end_col>0</end_col><end_row>22</end_row><start_col>0</start_col><start_row>22</start_row><x0>30</x0><x1>497</x1><y0>341</y0><y1>356</y1></tablecell><tablecell><dont_care>False</dont_care><end_col>0</end_col><end_row>23</end_row><start_col>0</start_col><start_row>23</start_row><x0>30</x0><x1>497</x1><y0>356</y0><y1>368</y1></tablecell><tablecell><dont_care>False</dont_care><end_col>0</end_col><end_row>24</end_row><start_col>0</start_col><start_row>24</start_row><x0>30</x0><x1>497</x1><y0>368</y0><y1>380</y1></tablecell><tablecell><dont_care>False</dont_care><end_col>0</end_col><end_row>25</end_row><start_col>0</start_col><start_row>25</start_row><x0>30</x0><x1>497</x1><y0>380</y0><y1>394</y1></tablecell><tablecell><dont_care>False</dont_care><end_col>0</end_col><end_row>26</end_row><start_col>0</start_col><start_row>26</start_row><x0>30</x0><x1>497</x1><y0>394</y0><y1>406</y1></tablecell><tablecell><dont_care>False</dont_care><end_col>0</end_col><end_row>27</end_row><start_col>0</start_col><start_row>27</start_row><x0>30</x0><x1>497</x1><y0>406</y0><y1>428</y1></tablecell><tablecell><dont_care>False</dont_care><end_col>0</end_col><end_row>28</end_row><start_col>0</start_col><start_row>28</start_row><x0>30</x0><x1>497</x1><y0>428</y0><y1>441</y1></tablecell><tablecell><dont_care>False</dont_care><end_col>0</end_col><end_row>29</end_row><start_col>0</start_col><start_row>29</start_row><x0>30</x0><x1>497</x1><y0>441</y0><y1>452</y1></tablecell><tablecell><dont_care>False</dont_care><end_col>0</end_col><end_row>30</end_row><start_col>0</start_col><start_row>30</start_row><x0>30</x0><x1>497</x1><y0>452</y0><y1>465</y1></tablecell><tablecell><dont_care>False</dont_care><end_col>0</end_col><end_row>31</end_row><start_col>0</start_col><start_row>31</start_row><x0>30</x0><x1>497</x1><y0>465</y0><y1>480</y1></tablecell><tablecell><dont_care>False</dont_care><end_col>0</end_col><end_row>32</end_row><start_col>0</start_col><start_row>32</start_row><x0>30</x0><x1>497</x1><y0>480</y0><y1>493</y1></tablecell><tablecell><dont_care>False</dont_care><end_col>0</end_col><end_row>33</end_row><start_col>0</start_col><start_row>33</start_row><x0>30</x0><x1>497</x1><y0>493</y0><y1>507</y1></tablecell><tablecell><dont_care>False</dont_care><end_col>0</end_col><end_row>34</end_row><start_col>0</start_col><start_row>34</start_row><x0>30</x0><x1>497</x1><y0>507</y0><y1>522</y1></tablecell><tablecell><dont_care>False</dont_care><end_col>0</end_col><end_row>35</end_row><start_col>0</start_col><start_row>35</start_row><x0>30</x0><x1>497</x1><y0>522</y0><y1>539</y1></tablecell><tablecell><dont_care>False</dont_care><end_col>0</end_col><end_row>36</end_row><start_col>0</start_col><start_row>36</start_row><x0>30</x0><x1>497</x1><y0>539</y0><y1>556</y1></tablecell><tablecell><dont_care>False</dont_care><end_col>0</end_col><end_row>37</end_row><start_col>0</start_col><start_row>37</start_row><x0>30</x0><x1>497</x1><y0>556</y0><y1>574</y1></tablecell><tablecell><dont_care>False</dont_care><end_col>0</end_col><end_row>38</end_row><start_col>0</start_col><start_row>38</start_row><x0>30</x0><x1>497</x1><y0>574</y0><y1>586</y1></tablecell><tablecell><dont_care>False</dont_care><end_col>0</end_col><end_row>39</end_row><start_col>0</start_col><start_row>39</start_row><x0>30</x0><x1>497</x1><y0>586</y0><y1>607</y1></tablecell><tablecell><dont_care>False</dont_care><end_col>0</end_col><end_row>40</end_row><start_col>0</start_col><start_row>40</start_row><x0>30</x0><x1>497</x1><y0>607</y0><y1>620</y1></tablecell><tablecell><dont_care>False</dont_care><end_col>0</end_col><end_row>41</end_row><start_col>0</start_col><start_row>41</start_row><x0>30</x0><x1>497</x1><y0>620</y0><y1>632</y1></tablecell><tablecell><dont_care>False</dont_care><end_col>0</end_col><end_row>42</end_row><start_col>0</start_col><start_row>42</start_row><x0>30</x0><x1>497</x1><y0>632</y0><y1>644</y1></tablecell><tablecell><dont_care>False</dont_care><end_col>0</end_col><end_row>43</end_row><start_col>0</start_col><start_row>43</start_row><x0>30</x0><x1>497</x1><y0>644</y0><y1>655</y1></tablecell><tablecell><dont_care>False</dont_care><end_col>0</end_col><end_row>44</end_row><start_col>0</start_col><start_row>44</start_row><x0>30</x0><x1>497</x1><y0>655</y0><y1>667</y1></tablecell><tablecell><dont_care>False</dont_care><end_col>0</end_col><end_row>45</end_row><start_col>0</start_col><start_row>45</start_row><x0>30</x0><x1>497</x1><y0>667</y0><y1>679</y1></tablecell><tablecell><dont_care>False</dont_care><end_col>0</end_col><end_row>46</end_row><start_col>0</start_col><start_row>46</start_row><x0>30</x0><x1>497</x1><y0>679</y0><y1>691</y1></tablecell><tablecell><dont_care>False</dont_care><end_col>0</end_col><end_row>47</end_row><start_col>0</start_col><start_row>47</start_row><x0>30</x0><x1>497</x1><y0>691</y0><y1>714</y1></tablecell><tablecell><dont_care>False</dont_care><end_col>0</end_col><end_row>48</end_row><start_col>0</start_col><start_row>48</start_row><x0>30</x0><x1>497</x1><y0>714</y0><y1>727</y1></tablecell><tablecell><dont_care>False</dont_care><end_col>0</end_col><end_row>49</end_row><start_col>0</start_col><start_row>49</start_row><x0>30</x0><x1>497</x1><y0>727</y0><y1>738</y1></tablecell><tablecell><dont_care>False</dont_care><end_col>0</end_col><end_row>50</end_row><start_col>0</start_col><start_row>50</start_row><x0>30</x0><x1>497</x1><y0>738</y0><y1>755</y1></tablecell><tablecell><dont_care>False</dont_care><end_col>3</end_col><end_row>0</end_row><start_col>1</start_col><start_row>0</start_row><x0>497</x0><x1>672</x1><y0>12</y0><y1>34</y1></tablecell><tablecell><dont_care>False</dont_care><end_col>1</end_col><end_row>1</end_row><start_col>1</start_col><start_row>1</start_row><x0>497</x0><x1>555</x1><y0>34</y0><y1>45</y1></tablecell><tablecell><dont_care>False</dont_care><end_col>1</end_col><end_row>2</end_row><start_col>1</start_col><start_row>2</start_row><x0>497</x0><x1>555</x1><y0>45</y0><y1>65</y1></tablecell><tablecell><dont_care>False</dont_care><end_col>1</end_col><end_row>3</end_row><start_col>1</start_col><start_row>3</start_row><x0>497</x0><x1>555</x1><y0>65</y0><y1>77</y1></tablecell><tablecell><dont_care>False</dont_care><end_col>1</end_col><end_row>4</end_row><start_col>1</start_col><start_row>4</start_row><x0>497</x0><x1>555</x1><y0>77</y0><y1>89</y1></tablecell><tablecell><dont_care>False</dont_care><end_col>1</end_col><end_row>5</end_row><start_col>1</start_col><start_row>5</start_row><x0>497</x0><x1>555</x1><y0>89</y0><y1>100</y1></tablecell><tablecell><dont_care>False</dont_care><end_col>1</end_col><end_row>6</end_row><start_col>1</start_col><start_row>6</start_row><x0>497</x0><x1>555</x1><y0>100</y0><y1>113</y1></tablecell><tablecell><dont_care>False</dont_care><end_col>1</end_col><end_row>7</end_row><start_col>1</start_col><start_row>7</start_row><x0>497</x0><x1>555</x1><y0>113</y0><y1>125</y1></tablecell><tablecell><dont_care>False</dont_care><end_col>1</end_col><end_row>8</end_row><start_col>1</start_col><start_row>8</start_row><x0>497</x0><x1>555</x1><y0>125</y0><y1>136</y1></tablecell><tablecell><dont_care>False</dont_care><end_col>1</end_col><end_row>9</end_row><start_col>1</start_col><start_row>9</start_row><x0>497</x0><x1>555</x1><y0>136</y0><y1>148</y1></tablecell><tablecell><dont_care>False</dont_care><end_col>1</end_col><end_row>10</end_row><start_col>1</start_col><start_row>10</start_row><x0>497</x0><x1>555</x1><y0>148</y0><y1>172</y1></tablecell><tablecell><dont_care>False</dont_care><end_col>1</end_col><end_row>11</end_row><start_col>1</start_col><start_row>11</start_row><x0>497</x0><x1>555</x1><y0>172</y0><y1>183</y1></tablecell><tablecell><dont_care>False</dont_care><end_col>1</end_col><end_row>12</end_row><start_col>1</start_col><start_row>12</start_row><x0>497</x0><x1>555</x1><y0>183</y0><y1>204</y1></tablecell><tablecell><dont_care>False</dont_care><end_col>1</end_col><end_row>13</end_row><start_col>1</start_col><start_row>13</start_row><x0>497</x0><x1>555</x1><y0>204</y0><y1>219</y1></tablecell><tablecell><dont_care>False</dont_care><end_col>1</end_col><end_row>14</end_row><start_col>1</start_col><start_row>14</start_row><x0>497</x0><x1>555</x1><y0>219</y0><y1>231</y1></tablecell><tablecell><dont_care>False</dont_care><end_col>1</end_col><end_row>15</end_row><start_col>1</start_col><start_row>15</start_row><x0>497</x0><x1>555</x1><y0>231</y0><y1>256</y1></tablecell><tablecell><dont_care>False</dont_care><end_col>1</end_col><end_row>16</end_row><start_col>1</start_col><start_row>16</start_row><x0>497</x0><x1>555</x1><y0>256</y0><y1>268</y1></tablecell><tablecell><dont_care>False</dont_care><end_col>1</end_col><end_row>17</end_row><start_col>1</start_col><start_row>17</start_row><x0>497</x0><x1>555</x1><y0>268</y0><y1>283</y1></tablecell><tablecell><dont_care>False</dont_care><end_col>1</end_col><end_row>18</end_row><start_col>1</start_col><start_row>18</start_row><x0>497</x0><x1>555</x1><y0>283</y0><y1>306</y1></tablecell><tablecell><dont_care>False</dont_care><end_col>1</end_col><end_row>19</end_row><start_col>1</start_col><start_row>19</start_row><x0>497</x0><x1>555</x1><y0>306</y0><y1>318</y1></tablecell><tablecell><dont_care>False</dont_care><end_col>1</end_col><end_row>20</end_row><start_col>1</start_col><start_row>20</start_row><x0>497</x0><x1>555</x1><y0>318</y0><y1>330</y1></tablecell><tablecell><dont_care>False</dont_care><end_col>1</end_col><end_row>21</end_row><start_col>1</start_col><start_row>21</start_row><x0>497</x0><x1>555</x1><y0>330</y0><y1>341</y1></tablecell><tablecell><dont_care>False</dont_care><end_col>1</end_col><end_row>22</end_row><start_col>1</start_col><start_row>22</start_row><x0>497</x0><x1>555</x1><y0>341</y0><y1>356</y1></tablecell><tablecell><dont_care>False</dont_care><end_col>1</end_col><end_row>23</end_row><start_col>1</start_col><start_row>23</start_row><x0>497</x0><x1>555</x1><y0>356</y0><y1>368</y1></tablecell><tablecell><dont_care>False</dont_care><end_col>1</end_col><end_row>24</end_row><start_col>1</start_col><start_row>24</start_row><x0>497</x0><x1>555</x1><y0>368</y0><y1>380</y1></tablecell><tablecell><dont_care>False</dont_care><end_col>1</end_col><end_row>25</end_row><start_col>1</start_col><start_row>25</start_row><x0>497</x0><x1>555</x1><y0>380</y0><y1>394</y1></tablecell><tablecell><dont_care>False</dont_care><end_col>1</end_col><end_row>26</end_row><start_col>1</start_col><start_row>26</start_row><x0>497</x0><x1>555</x1><y0>394</y0><y1>406</y1></tablecell><tablecell><dont_care>False</dont_care><end_col>1</end_col><end_row>27</end_row><start_col>1</start_col><start_row>27</start_row><x0>497</x0><x1>555</x1><y0>406</y0><y1>428</y1></tablecell><tablecell><dont_care>False</dont_care><end_col>1</end_col><end_row>28</end_row><start_col>1</start_col><start_row>28</start_row><x0>497</x0><x1>555</x1><y0>428</y0><y1>441</y1></tablecell><tablecell><dont_care>False</dont_care><end_col>1</end_col><end_row>29</end_row><start_col>1</start_col><start_row>29</start_row><x0>497</x0><x1>555</x1><y0>441</y0><y1>452</y1></tablecell><tablecell><dont_care>False</dont_care><end_col>1</end_col><end_row>30</end_row><start_col>1</start_col><start_row>30</start_row><x0>497</x0><x1>555</x1><y0>452</y0><y1>465</y1></tablecell><tablecell><dont_care>False</dont_care><end_col>1</end_col><end_row>31</end_row><start_col>1</start_col><start_row>31</start_row><x0>497</x0><x1>555</x1><y0>465</y0><y1>480</y1></tablecell><tablecell><dont_care>False</dont_care><end_col>1</end_col><end_row>32</end_row><start_col>1</start_col><start_row>32</start_row><x0>497</x0><x1>555</x1><y0>480</y0><y1>493</y1></tablecell><tablecell><dont_care>False</dont_care><end_col>1</end_col><end_row>33</end_row><start_col>1</start_col><start_row>33</start_row><x0>497</x0><x1>555</x1><y0>493</y0><y1>507</y1></tablecell><tablecell><dont_care>False</dont_care><end_col>1</end_col><end_row>34</end_row><start_col>1</start_col><start_row>34</start_row><x0>497</x0><x1>555</x1><y0>507</y0><y1>522</y1></tablecell><tablecell><dont_care>False</dont_care><end_col>1</end_col><end_row>35</end_row><start_col>1</start_col><start_row>35</start_row><x0>497</x0><x1>555</x1><y0>522</y0><y1>539</y1></tablecell><tablecell><dont_care>False</dont_care><end_col>1</end_col><end_row>36</end_row><start_col>1</start_col><start_row>36</start_row><x0>497</x0><x1>555</x1><y0>539</y0><y1>556</y1></tablecell><tablecell><dont_care>False</dont_care><end_col>1</end_col><end_row>37</end_row><start_col>1</start_col><start_row>37</start_row><x0>497</x0><x1>555</x1><y0>556</y0><y1>574</y1></tablecell><tablecell><dont_care>False</dont_care><end_col>1</end_col><end_row>38</end_row><start_col>1</start_col><start_row>38</start_row><x0>497</x0><x1>555</x1><y0>574</y0><y1>586</y1></tablecell><tablecell><dont_care>False</dont_care><end_col>1</end_col><end_row>39</end_row><start_col>1</start_col><start_row>39</start_row><x0>497</x0><x1>555</x1><y0>586</y0><y1>607</y1></tablecell><tablecell><dont_care>False</dont_care><end_col>1</end_col><end_row>40</end_row><start_col>1</start_col><start_row>40</start_row><x0>497</x0><x1>555</x1><y0>607</y0><y1>620</y1></tablecell><tablecell><dont_care>False</dont_care><end_col>1</end_col><end_row>41</end_row><start_col>1</start_col><start_row>41</start_row><x0>497</x0><x1>555</x1><y0>620</y0><y1>632</y1></tablecell><tablecell><dont_care>False</dont_care><end_col>1</end_col><end_row>42</end_row><start_col>1</start_col><start_row>42</start_row><x0>497</x0><x1>555</x1><y0>632</y0><y1>644</y1></tablecell><tablecell><dont_care>False</dont_care><end_col>1</end_col><end_row>43</end_row><start_col>1</start_col><start_row>43</start_row><x0>497</x0><x1>555</x1><y0>644</y0><y1>655</y1></tablecell><tablecell><dont_care>False</dont_care><end_col>1</end_col><end_row>44</end_row><start_col>1</start_col><start_row>44</start_row><x0>497</x0><x1>555</x1><y0>655</y0><y1>667</y1></tablecell><tablecell><dont_care>False</dont_care><end_col>1</end_col><end_row>45</end_row><start_col>1</start_col><start_row>45</start_row><x0>497</x0><x1>555</x1><y0>667</y0><y1>679</y1></tablecell><tablecell><dont_care>False</dont_care><end_col>1</end_col><end_row>46</end_row><start_col>1</start_col><start_row>46</start_row><x0>497</x0><x1>555</x1><y0>679</y0><y1>691</y1></tablecell><tablecell><dont_care>False</dont_care><end_col>1</end_col><end_row>47</end_row><start_col>1</start_col><start_row>47</start_row><x0>497</x0><x1>555</x1><y0>691</y0><y1>714</y1></tablecell><tablecell><dont_care>False</dont_care><end_col>1</end_col><end_row>48</end_row><start_col>1</start_col><start_row>48</start_row><x0>497</x0><x1>555</x1><y0>714</y0><y1>727</y1></tablecell><tablecell><dont_care>False</dont_care><end_col>1</end_col><end_row>49</end_row><start_col>1</start_col><start_row>49</start_row><x0>497</x0><x1>555</x1><y0>727</y0><y1>738</y1></tablecell><tablecell><dont_care>False</dont_care><end_col>1</end_col><end_row>50</end_row><start_col>1</start_col><start_row>50</start_row><x0>497</x0><x1>555</x1><y0>738</y0><y1>755</y1></tablecell><tablecell><dont_care>False</dont_care><end_col>2</end_col><end_row>1</end_row><start_col>2</start_col><start_row>1</start_row><x0>555</x0><x1>613</x1><y0>34</y0><y1>45</y1></tablecell><tablecell><dont_care>False</dont_care><end_col>2</end_col><end_row>2</end_row><start_col>2</start_col><start_row>2</start_row><x0>555</x0><x1>613</x1><y0>45</y0><y1>65</y1></tablecell><tablecell><dont_care>False</dont_care><end_col>2</end_col><end_row>3</end_row><start_col>2</start_col><start_row>3</start_row><x0>555</x0><x1>613</x1><y0>65</y0><y1>77</y1></tablecell><tablecell><dont_care>False</dont_care><end_col>2</end_col><end_row>4</end_row><start_col>2</start_col><start_row>4</start_row><x0>555</x0><x1>613</x1><y0>77</y0><y1>89</y1></tablecell><tablecell><dont_care>False</dont_care><end_col>2</end_col><end_row>5</end_row><start_col>2</start_col><start_row>5</start_row><x0>555</x0><x1>613</x1><y0>89</y0><y1>100</y1></tablecell><tablecell><dont_care>False</dont_care><end_col>2</end_col><end_row>6</end_row><start_col>2</start_col><start_row>6</start_row><x0>555</x0><x1>613</x1><y0>100</y0><y1>113</y1></tablecell><tablecell><dont_care>False</dont_care><end_col>2</end_col><end_row>7</end_row><start_col>2</start_col><start_row>7</start_row><x0>555</x0><x1>613</x1><y0>113</y0><y1>125</y1></tablecell><tablecell><dont_care>False</dont_care><end_col>2</end_col><end_row>8</end_row><start_col>2</start_col><start_row>8</start_row><x0>555</x0><x1>613</x1><y0>125</y0><y1>136</y1></tablecell><tablecell><dont_care>False</dont_care><end_col>2</end_col><end_row>9</end_row><start_col>2</start_col><start_row>9</start_row><x0>555</x0><x1>613</x1><y0>136</y0><y1>148</y1></tablecell><tablecell><dont_care>False</dont_care><end_col>2</end_col><end_row>10</end_row><start_col>2</start_col><start_row>10</start_row><x0>555</x0><x1>613</x1><y0>148</y0><y1>172</y1></tablecell><tablecell><dont_care>False</dont_care><end_col>2</end_col><end_row>11</end_row><start_col>2</start_col><start_row>11</start_row><x0>555</x0><x1>613</x1><y0>172</y0><y1>183</y1></tablecell><tablecell><dont_care>False</dont_care><end_col>2</end_col><end_row>12</end_row><start_col>2</start_col><start_row>12</start_row><x0>555</x0><x1>613</x1><y0>183</y0><y1>204</y1></tablecell><tablecell><dont_care>False</dont_care><end_col>2</end_col><end_row>13</end_row><start_col>2</start_col><start_row>13</start_row><x0>555</x0><x1>613</x1><y0>204</y0><y1>219</y1></tablecell><tablecell><dont_care>False</dont_care><end_col>2</end_col><end_row>14</end_row><start_col>2</start_col><start_row>14</start_row><x0>555</x0><x1>613</x1><y0>219</y0><y1>231</y1></tablecell><tablecell><dont_care>False</dont_care><end_col>2</end_col><end_row>15</end_row><start_col>2</start_col><start_row>15</start_row><x0>555</x0><x1>613</x1><y0>231</y0><y1>256</y1></tablecell><tablecell><dont_care>False</dont_care><end_col>2</end_col><end_row>16</end_row><start_col>2</start_col><start_row>16</start_row><x0>555</x0><x1>613</x1><y0>256</y0><y1>268</y1></tablecell><tablecell><dont_care>False</dont_care><end_col>2</end_col><end_row>17</end_row><start_col>2</start_col><start_row>17</start_row><x0>555</x0><x1>613</x1><y0>268</y0><y1>283</y1></tablecell><tablecell><dont_care>False</dont_care><end_col>2</end_col><end_row>18</end_row><start_col>2</start_col><start_row>18</start_row><x0>555</x0><x1>613</x1><y0>283</y0><y1>306</y1></tablecell><tablecell><dont_care>False</dont_care><end_col>2</end_col><end_row>19</end_row><start_col>2</start_col><start_row>19</start_row><x0>555</x0><x1>613</x1><y0>306</y0><y1>318</y1></tablecell><tablecell><dont_care>False</dont_care><end_col>2</end_col><end_row>20</end_row><start_col>2</start_col><start_row>20</start_row><x0>555</x0><x1>613</x1><y0>318</y0><y1>330</y1></tablecell><tablecell><dont_care>False</dont_care><end_col>2</end_col><end_row>21</end_row><start_col>2</start_col><start_row>21</start_row><x0>555</x0><x1>613</x1><y0>330</y0><y1>341</y1></tablecell><tablecell><dont_care>False</dont_care><end_col>2</end_col><end_row>22</end_row><start_col>2</start_col><start_row>22</start_row><x0>555</x0><x1>613</x1><y0>341</y0><y1>356</y1></tablecell><tablecell><dont_care>False</dont_care><end_col>2</end_col><end_row>23</end_row><start_col>2</start_col><start_row>23</start_row><x0>555</x0><x1>613</x1><y0>356</y0><y1>368</y1></tablecell><tablecell><dont_care>False</dont_care><end_col>2</end_col><end_row>24</end_row><start_col>2</start_col><start_row>24</start_row><x0>555</x0><x1>613</x1><y0>368</y0><y1>380</y1></tablecell><tablecell><dont_care>False</dont_care><end_col>2</end_col><end_row>25</end_row><start_col>2</start_col><start_row>25</start_row><x0>555</x0><x1>613</x1><y0>380</y0><y1>394</y1></tablecell><tablecell><dont_care>False</dont_care><end_col>2</end_col><end_row>26</end_row><start_col>2</start_col><start_row>26</start_row><x0>555</x0><x1>613</x1><y0>394</y0><y1>406</y1></tablecell><tablecell><dont_care>False</dont_care><end_col>2</end_col><end_row>27</end_row><start_col>2</start_col><start_row>27</start_row><x0>555</x0><x1>613</x1><y0>406</y0><y1>428</y1></tablecell><tablecell><dont_care>False</dont_care><end_col>2</end_col><end_row>28</end_row><start_col>2</start_col><start_row>28</start_row><x0>555</x0><x1>613</x1><y0>428</y0><y1>441</y1></tablecell><tablecell><dont_care>False</dont_care><end_col>2</end_col><end_row>29</end_row><start_col>2</start_col><start_row>29</start_row><x0>555</x0><x1>613</x1><y0>441</y0><y1>452</y1></tablecell><tablecell><dont_care>False</dont_care><end_col>2</end_col><end_row>30</end_row><start_col>2</start_col><start_row>30</start_row><x0>555</x0><x1>613</x1><y0>452</y0><y1>465</y1></tablecell><tablecell><dont_care>False</dont_care><end_col>2</end_col><end_row>31</end_row><start_col>2</start_col><start_row>31</start_row><x0>555</x0><x1>613</x1><y0>465</y0><y1>480</y1></tablecell><tablecell><dont_care>False</dont_care><end_col>2</end_col><end_row>32</end_row><start_col>2</start_col><start_row>32</start_row><x0>555</x0><x1>613</x1><y0>480</y0><y1>493</y1></tablecell><tablecell><dont_care>False</dont_care><end_col>2</end_col><end_row>33</end_row><start_col>2</start_col><start_row>33</start_row><x0>555</x0><x1>613</x1><y0>493</y0><y1>507</y1></tablecell><tablecell><dont_care>False</dont_care><end_col>2</end_col><end_row>34</end_row><start_col>2</start_col><start_row>34</start_row><x0>555</x0><x1>613</x1><y0>507</y0><y1>522</y1></tablecell><tablecell><dont_care>False</dont_care><end_col>2</end_col><end_row>35</end_row><start_col>2</start_col><start_row>35</start_row><x0>555</x0><x1>613</x1><y0>522</y0><y1>539</y1></tablecell><tablecell><dont_care>False</dont_care><end_col>2</end_col><end_row>36</end_row><start_col>2</start_col><start_row>36</start_row><x0>555</x0><x1>613</x1><y0>539</y0><y1>556</y1></tablecell><tablecell><dont_care>False</dont_care><end_col>2</end_col><end_row>37</end_row><start_col>2</start_col><start_row>37</start_row><x0>555</x0><x1>613</x1><y0>556</y0><y1>574</y1></tablecell><tablecell><dont_care>False</dont_care><end_col>2</end_col><end_row>38</end_row><start_col>2</start_col><start_row>38</start_row><x0>555</x0><x1>613</x1><y0>574</y0><y1>586</y1></tablecell><tablecell><dont_care>False</dont_care><end_col>2</end_col><end_row>39</end_row><start_col>2</start_col><start_row>39</start_row><x0>555</x0><x1>613</x1><y0>586</y0><y1>607</y1></tablecell><tablecell><dont_care>False</dont_care><end_col>2</end_col><end_row>40</end_row><start_col>2</start_col><start_row>40</start_row><x0>555</x0><x1>613</x1><y0>607</y0><y1>620</y1></tablecell><tablecell><dont_care>False</dont_care><end_col>2</end_col><end_row>41</end_row><start_col>2</start_col><start_row>41</start_row><x0>555</x0><x1>613</x1><y0>620</y0><y1>632</y1></tablecell><tablecell><dont_care>False</dont_care><end_col>2</end_col><end_row>42</end_row><start_col>2</start_col><start_row>42</start_row><x0>555</x0><x1>613</x1><y0>632</y0><y1>644</y1></tablecell><tablecell><dont_care>False</dont_care><end_col>2</end_col><end_row>43</end_row><start_col>2</start_col><start_row>43</start_row><x0>555</x0><x1>613</x1><y0>644</y0><y1>655</y1></tablecell><tablecell><dont_care>False</dont_care><end_col>2</end_col><end_row>44</end_row><start_col>2</start_col><start_row>44</start_row><x0>555</x0><x1>613</x1><y0>655</y0><y1>667</y1></tablecell><tablecell><dont_care>False</dont_care><end_col>2</end_col><end_row>45</end_row><start_col>2</start_col><start_row>45</start_row><x0>555</x0><x1>613</x1><y0>667</y0><y1>679</y1></tablecell><tablecell><dont_care>False</dont_care><end_col>2</end_col><end_row>46</end_row><start_col>2</start_col><start_row>46</start_row><x0>555</x0><x1>613</x1><y0>679</y0><y1>691</y1></tablecell><tablecell><dont_care>False</dont_care><end_col>2</end_col><end_row>47</end_row><start_col>2</start_col><start_row>47</start_row><x0>555</x0><x1>613</x1><y0>691</y0><y1>714</y1></tablecell><tablecell><dont_care>False</dont_care><end_col>2</end_col><end_row>48</end_row><start_col>2</start_col><start_row>48</start_row><x0>555</x0><x1>613</x1><y0>714</y0><y1>727</y1></tablecell><tablecell><dont_care>False</dont_care><end_col>2</end_col><end_row>49</end_row><start_col>2</start_col><start_row>49</start_row><x0>555</x0><x1>613</x1><y0>727</y0><y1>738</y1></tablecell><tablecell><dont_care>False</dont_care><end_col>2</end_col><end_row>50</end_row><start_col>2</start_col><start_row>50</start_row><x0>555</x0><x1>613</x1><y0>738</y0><y1>755</y1></tablecell><tablecell><dont_care>False</dont_care><end_col>3</end_col><end_row>1</end_row><start_col>3</start_col><start_row>1</start_row><x0>613</x0><x1>672</x1><y0>34</y0><y1>45</y1></tablecell><tablecell><dont_care>False</dont_care><end_col>3</end_col><end_row>2</end_row><start_col>3</start_col><start_row>2</start_row><x0>613</x0><x1>672</x1><y0>45</y0><y1>65</y1></tablecell><tablecell><dont_care>False</dont_care><end_col>3</end_col><end_row>3</end_row><start_col>3</start_col><start_row>3</start_row><x0>613</x0><x1>672</x1><y0>65</y0><y1>77</y1></tablecell><tablecell><dont_care>False</dont_care><end_col>3</end_col><end_row>4</end_row><start_col>3</start_col><start_row>4</start_row><x0>613</x0><x1>672</x1><y0>77</y0><y1>89</y1></tablecell><tablecell><dont_care>False</dont_care><end_col>3</end_col><end_row>5</end_row><start_col>3</start_col><start_row>5</start_row><x0>613</x0><x1>672</x1><y0>89</y0><y1>100</y1></tablecell><tablecell><dont_care>False</dont_care><end_col>3</end_col><end_row>6</end_row><start_col>3</start_col><start_row>6</start_row><x0>613</x0><x1>672</x1><y0>100</y0><y1>113</y1></tablecell><tablecell><dont_care>False</dont_care><end_col>3</end_col><end_row>7</end_row><start_col>3</start_col><start_row>7</start_row><x0>613</x0><x1>672</x1><y0>113</y0><y1>125</y1></tablecell><tablecell><dont_care>False</dont_care><end_col>3</end_col><end_row>8</end_row><start_col>3</start_col><start_row>8</start_row><x0>613</x0><x1>672</x1><y0>125</y0><y1>136</y1></tablecell><tablecell><dont_care>False</dont_care><end_col>3</end_col><end_row>9</end_row><start_col>3</start_col><start_row>9</start_row><x0>613</x0><x1>672</x1><y0>136</y0><y1>148</y1></tablecell><tablecell><dont_care>False</dont_care><end_col>3</end_col><end_row>10</end_row><start_col>3</start_col><start_row>10</start_row><x0>613</x0><x1>672</x1><y0>148</y0><y1>172</y1></tablecell><tablecell><dont_care>False</dont_care><end_col>3</end_col><end_row>11</end_row><start_col>3</start_col><start_row>11</start_row><x0>613</x0><x1>672</x1><y0>172</y0><y1>183</y1></tablecell><tablecell><dont_care>False</dont_care><end_col>3</end_col><end_row>12</end_row><start_col>3</start_col><start_row>12</start_row><x0>613</x0><x1>672</x1><y0>183</y0><y1>204</y1></tablecell><tablecell><dont_care>False</dont_care><end_col>3</end_col><end_row>13</end_row><start_col>3</start_col><start_row>13</start_row><x0>613</x0><x1>672</x1><y0>204</y0><y1>219</y1></tablecell><tablecell><dont_care>False</dont_care><end_col>3</end_col><end_row>14</end_row><start_col>3</start_col><start_row>14</start_row><x0>613</x0><x1>672</x1><y0>219</y0><y1>231</y1></tablecell><tablecell><dont_care>False</dont_care><end_col>3</end_col><end_row>15</end_row><start_col>3</start_col><start_row>15</start_row><x0>613</x0><x1>672</x1><y0>231</y0><y1>256</y1></tablecell><tablecell><dont_care>False</dont_care><end_col>3</end_col><end_row>16</end_row><start_col>3</start_col><start_row>16</start_row><x0>613</x0><x1>672</x1><y0>256</y0><y1>268</y1></tablecell><tablecell><dont_care>False</dont_care><end_col>3</end_col><end_row>17</end_row><start_col>3</start_col><start_row>17</start_row><x0>613</x0><x1>672</x1><y0>268</y0><y1>283</y1></tablecell><tablecell><dont_care>False</dont_care><end_col>3</end_col><end_row>18</end_row><start_col>3</start_col><start_row>18</start_row><x0>613</x0><x1>672</x1><y0>283</y0><y1>306</y1></tablecell><tablecell><dont_care>False</dont_care><end_col>3</end_col><end_row>19</end_row><start_col>3</start_col><start_row>19</start_row><x0>613</x0><x1>672</x1><y0>306</y0><y1>318</y1></tablecell><tablecell><dont_care>False</dont_care><end_col>3</end_col><end_row>20</end_row><start_col>3</start_col><start_row>20</start_row><x0>613</x0><x1>672</x1><y0>318</y0><y1>330</y1></tablecell><tablecell><dont_care>False</dont_care><end_col>3</end_col><end_row>21</end_row><start_col>3</start_col><start_row>21</start_row><x0>613</x0><x1>672</x1><y0>330</y0><y1>341</y1></tablecell><tablecell><dont_care>False</dont_care><end_col>3</end_col><end_row>22</end_row><start_col>3</start_col><start_row>22</start_row><x0>613</x0><x1>672</x1><y0>341</y0><y1>356</y1></tablecell><tablecell><dont_care>False</dont_care><end_col>3</end_col><end_row>23</end_row><start_col>3</start_col><start_row>23</start_row><x0>613</x0><x1>672</x1><y0>356</y0><y1>368</y1></tablecell><tablecell><dont_care>False</dont_care><end_col>3</end_col><end_row>24</end_row><start_col>3</start_col><start_row>24</start_row><x0>613</x0><x1>672</x1><y0>368</y0><y1>380</y1></tablecell><tablecell><dont_care>False</dont_care><end_col>3</end_col><end_row>25</end_row><start_col>3</start_col><start_row>25</start_row><x0>613</x0><x1>672</x1><y0>380</y0><y1>394</y1></tablecell><tablecell><dont_care>False</dont_care><end_col>3</end_col><end_row>26</end_row><start_col>3</start_col><start_row>26</start_row><x0>613</x0><x1>672</x1><y0>394</y0><y1>406</y1></tablecell><tablecell><dont_care>False</dont_care><end_col>3</end_col><end_row>27</end_row><start_col>3</start_col><start_row>27</start_row><x0>613</x0><x1>672</x1><y0>406</y0><y1>428</y1></tablecell><tablecell><dont_care>False</dont_care><end_col>3</end_col><end_row>28</end_row><start_col>3</start_col><start_row>28</start_row><x0>613</x0><x1>672</x1><y0>428</y0><y1>441</y1></tablecell><tablecell><dont_care>False</dont_care><end_col>3</end_col><end_row>29</end_row><start_col>3</start_col><start_row>29</start_row><x0>613</x0><x1>672</x1><y0>441</y0><y1>452</y1></tablecell><tablecell><dont_care>False</dont_care><end_col>3</end_col><end_row>30</end_row><start_col>3</start_col><start_row>30</start_row><x0>613</x0><x1>672</x1><y0>452</y0><y1>465</y1></tablecell><tablecell><dont_care>False</dont_care><end_col>3</end_col><end_row>31</end_row><start_col>3</start_col><start_row>31</start_row><x0>613</x0><x1>672</x1><y0>465</y0><y1>480</y1></tablecell><tablecell><dont_care>False</dont_care><end_col>3</end_col><end_row>32</end_row><start_col>3</start_col><start_row>32</start_row><x0>613</x0><x1>672</x1><y0>480</y0><y1>493</y1></tablecell><tablecell><dont_care>False</dont_care><end_col>3</end_col><end_row>33</end_row><start_col>3</start_col><start_row>33</start_row><x0>613</x0><x1>672</x1><y0>493</y0><y1>507</y1></tablecell><tablecell><dont_care>False</dont_care><end_col>3</end_col><end_row>34</end_row><start_col>3</start_col><start_row>34</start_row><x0>613</x0><x1>672</x1><y0>507</y0><y1>522</y1></tablecell><tablecell><dont_care>False</dont_care><end_col>3</end_col><end_row>35</end_row><start_col>3</start_col><start_row>35</start_row><x0>613</x0><x1>672</x1><y0>522</y0><y1>539</y1></tablecell><tablecell><dont_care>False</dont_care><end_col>3</end_col><end_row>36</end_row><start_col>3</start_col><start_row>36</start_row><x0>613</x0><x1>672</x1><y0>539</y0><y1>556</y1></tablecell><tablecell><dont_care>False</dont_care><end_col>3</end_col><end_row>37</end_row><start_col>3</start_col><start_row>37</start_row><x0>613</x0><x1>672</x1><y0>556</y0><y1>574</y1></tablecell><tablecell><dont_care>False</dont_care><end_col>3</end_col><end_row>38</end_row><start_col>3</start_col><start_row>38</start_row><x0>613</x0><x1>672</x1><y0>574</y0><y1>586</y1></tablecell><tablecell><dont_care>False</dont_care><end_col>3</end_col><end_row>39</end_row><start_col>3</start_col><start_row>39</start_row><x0>613</x0><x1>672</x1><y0>586</y0><y1>607</y1></tablecell><tablecell><dont_care>False</dont_care><end_col>3</end_col><end_row>40</end_row><start_col>3</start_col><start_row>40</start_row><x0>613</x0><x1>672</x1><y0>607</y0><y1>620</y1></tablecell><tablecell><dont_care>False</dont_care><end_col>3</end_col><end_row>41</end_row><start_col>3</start_col><start_row>41</start_row><x0>613</x0><x1>672</x1><y0>620</y0><y1>632</y1></tablecell><tablecell><dont_care>False</dont_care><end_col>3</end_col><end_row>42</end_row><start_col>3</start_col><start_row>42</start_row><x0>613</x0><x1>672</x1><y0>632</y0><y1>644</y1></tablecell><tablecell><dont_care>False</dont_care><end_col>3</end_col><end_row>43</end_row><start_col>3</start_col><start_row>43</start_row><x0>613</x0><x1>672</x1><y0>644</y0><y1>655</y1></tablecell><tablecell><dont_care>False</dont_care><end_col>3</end_col><end_row>44</end_row><start_col>3</start_col><start_row>44</start_row><x0>613</x0><x1>672</x1><y0>655</y0><y1>667</y1></tablecell><tablecell><dont_care>False</dont_care><end_col>3</end_col><end_row>45</end_row><start_col>3</start_col><start_row>45</start_row><x0>613</x0><x1>672</x1><y0>667</y0><y1>679</y1></tablecell><tablecell><dont_care>False</dont_care><end_col>3</end_col><end_row>46</end_row><start_col>3</start_col><start_row>46</start_row><x0>613</x0><x1>672</x1><y0>679</y0><y1>691</y1></tablecell><tablecell><dont_care>False</dont_care><end_col>3</end_col><end_row>47</end_row><start_col>3</start_col><start_row>47</start_row><x0>613</x0><x1>672</x1><y0>691</y0><y1>714</y1></tablecell><tablecell><dont_care>False</dont_care><end_col>3</end_col><end_row>48</end_row><start_col>3</start_col><start_row>48</start_row><x0>613</x0><x1>672</x1><y0>714</y0><y1>727</y1></tablecell><tablecell><dont_care>False</dont_care><end_col>3</end_col><end_row>49</end_row><start_col>3</start_col><start_row>49</start_row><x0>613</x0><x1>672</x1><y0>727</y0><y1>738</y1></tablecell><tablecell><dont_care>False</dont_care><end_col>3</end_col><end_row>50</end_row><start_col>3</start_col><start_row>50</start_row><x0>613</x0><x1>672</x1><y0>738</y0><y1>755</y1></tablecell></cells></object></annotation>